Workbook

Sheet Peer Comparison
A1: MINING PEER COMPARISON — ILLUSTRATIVE TEMPLATE (placeholder figures for demonstration; replace with cited actuals)
A2: Blue = input (replace with sourced figure). Black = formula. Demo artifact for the AllWeather presentation — not investment advice.
A4: Company | B4: Commodity | C4: Revenue (R'm) | D4: EBITDA (R'm) | E4: EBITDA margin | F4: HEPS (c) | G4: DPS (c) | H4: Div cover | I4: Net debt (R'm) | J4: Net debt/EBITDA | K4: FCF (R'm) | L4: Mkt cap (R'm) | M4: FCF yield | N4: Source
A5: Anglo American | B5: Diversified | C5: 600000 | D5: 180000 | E5: =D5/C5 -> 0.3 | F5: 2500 | G5: 1000 | H5: =IF(G5>0,F5/G5,"n/a") -> 2.5 | I5: 90000 | J5: =I5/D5 -> 0.5 | K5: 60000 | L5: 700000 | M5: =K5/L5 -> 0.085714286 | N5: Illustrative — replace with cited actuals
A6: BHP | B6: Diversified | C6: 1000000 | D6: 500000 | E6: =D6/C6 -> 0.5 | F6: 4500 | G6: 2800 | H6: =IF(G6>0,F6/G6,"n/a") -> 1.6071429 | I6: 200000 | J6: =I6/D6 -> 0.4 | K6: 220000 | L6: 2500000 | M6: =K6/L6 -> 0.088 | N6: Illustrative — replace with cited actuals
A7: Sasol | B7: Energy & chemicals | C7: 280000 | D7: 70000 | E7: =D7/C7 -> 0.25 | F7: 1800 | G7: 0 | H7: =IF(G7>0,F7/G7,"n/a") -> n/a | I7: 110000 | J7: =I7/D7 -> 1.5714286 | K7: 15000 | L7: 90000 | M7: =K7/L7 -> 0.16666667 | N7: Illustrative — replace with cited actuals
A8: Gold Fields | B8: Gold | C8: 150000 | D8: 65000 | E8: =D8/C8 -> 0.43333333 | F8: 1500 | G8: 700 | H8: =IF(G8>0,F8/G8,"n/a") -> 2.1428571 | I8: 20000 | J8: =I8/D8 -> 0.30769231 | K8: 18000 | L8: 200000 | M8: =K8/L8 -> 0.09 | N8: Illustrative — replace with cited actuals
A9: Exxaro | B9: Coal | C9: 80000 | D9: 25000 | E9: =D9/C9 -> 0.3125 | F9: 3500 | G9: 1800 | H9: =IF(G9>0,F9/G9,"n/a") -> 1.9444444 | I9: -5000 | J9: =I9/D9 -> -0.2 | K9: 9000 | L9: 70000 | M9: =K9/L9 -> 0.12857143 | N9: Illustrative — replace with cited actuals

Sheet Ratios & Flags
A1: RATIOS & RED-FLAGS — ILLUSTRATIVE (pulls from Peer Comparison)
A3: Company | B3: EBITDA margin | C3: Net debt/EBITDA | D3: FCF yield | E3: Div cover | F3: Leverage flag
A4: ='Peer Comparison'!A5 -> Anglo American | B4: ='Peer Comparison'!E5 -> 0.3 | C4: ='Peer Comparison'!J5 -> 0.5 | D4: ='Peer Comparison'!M5 -> 0.085714286 | E4: ='Peer Comparison'!H5 -> 2.5 | F4: =IF('Peer Comparison'!J5<=0,"Net cash",IF('Peer Comparison'!J5<0.75,"Low",IF('Peer Comparison'!J5<=1.5,"Moderate","High"))) -> Low
A5: ='Peer Comparison'!A6 -> BHP | B5: ='Peer Comparison'!E6 -> 0.5 | C5: ='Peer Comparison'!J6 -> 0.4 | D5: ='Peer Comparison'!M6 -> 0.088 | E5: ='Peer Comparison'!H6 -> 1.6071429 | F5: =IF('Peer Comparison'!J6<=0,"Net cash",IF('Peer Comparison'!J6<0.75,"Low",IF('Peer Comparison'!J6<=1.5,"Moderate","High"))) -> Low
A6: ='Peer Comparison'!A7 -> Sasol | B6: ='Peer Comparison'!E7 -> 0.25 | C6: ='Peer Comparison'!J7 -> 1.5714286 | D6: ='Peer Comparison'!M7 -> 0.16666667 | E6: ='Peer Comparison'!H7 -> n/a | F6: =IF('Peer Comparison'!J7<=0,"Net cash",IF('Peer Comparison'!J7<0.75,"Low",IF('Peer Comparison'!J7<=1.5,"Moderate","High"))) -> High
A7: ='Peer Comparison'!A8 -> Gold Fields | B7: ='Peer Comparison'!E8 -> 0.43333333 | C7: ='Peer Comparison'!J8 -> 0.30769231 | D7: ='Peer Comparison'!M8 -> 0.09 | E7: ='Peer Comparison'!H8 -> 2.1428571 | F7: =IF('Peer Comparison'!J8<=0,"Net cash",IF('Peer Comparison'!J8<0.75,"Low",IF('Peer Comparison'!J8<=1.5,"Moderate","High"))) -> Low
A8: ='Peer Comparison'!A9 -> Exxaro | B8: ='Peer Comparison'!E9 -> 0.3125 | C8: ='Peer Comparison'!J9 -> -0.2 | D8: ='Peer Comparison'!M9 -> 0.12857143 | E8: ='Peer Comparison'!H9 -> 1.9444444 | F8: =IF('Peer Comparison'!J9<=0,"Net cash",IF('Peer Comparison'!J9<0.75,"Low",IF('Peer Comparison'!J9<=1.5,"Moderate","High"))) -> Net cash
A10: Flag thresholds (illustrative): Net debt/EBITDA >1.5x High (red) · 0.75–1.5x Moderate (amber) · <0.75x Low (green) · ≤0 Net cash.
