Workbook

Sheet Cover
B2: SHOPRITE HOLDINGS LIMITED (JSE: SHP)
B3: Hormuz Scenario Model — 12–18 month projections (FY2026e–FY2027e)
B4: Investment Committee working model • 17 June 2026 • Internal research — for information only
B6: HOW TO USE THIS MODEL
B7: • Change only the BLUE cells (Assumptions tab). All BLACK cells are formulas; GREEN cells link across sheets.
B8: • Three scenarios run side-by-side: Scenario A (Strait of Hormuz open / peace holds), a middle Base case,
B9: and Scenario B (Strait closes again and stays shut / oil shock persists). Each is modelled for FY2026e & FY2027e.
B10: • FY2025A is the anchor. Exact reported actuals are on the 'FY2025 Actuals' tab (sacred — do not edit).
B11: • 'Macro Deck' holds the dated oil / rand / rates / fuel context behind the scenario assumptions.
B13: METHODOLOGY (transparent, driver-based)
B14: • Sale of merchandise = prior year × (1 + internal selling-price inflation + real volume/space growth).
B15: • Gross & trading profit = sale of merchandise × the respective margin assumption.
... B22: FY2025A ANCHOR (reported, continuing ops — see 'FY2025 Actuals')
B23: Sale of merchandise | D23: R252.7bn (+8.9%)
B24: Trading profit / margin | D24: R15.0bn (+16.6%) / 5.9%
B25: Diluted HEPS (continuing) | D25: 1,367.2c (+15.8%)
B26: DPS (1.75x cover) | D26: 781c (+9.7%)
B27: Net cash / borrowings | D27: R8.1bn net cash / R7.0bn debt
B28: Net finance costs | D28: R4.8bn (+30.9%)
B29: ROE / ROIC / WACC | D29: 26.7% / 19.4% / 13.5%
B31: SOURCES
B32: SH1 Shoprite reviewed results, 52 weeks ended 29 June 2025 (held locally; FY2024 restated IFRS 5).
B33: companies/shoprite/annual-reports/shoprite-annual-report-fy2025-20250902.txt
B34: Companion note: Shoprite_Holdings_SHP_12-18m_Outlook_Hormuz_Scenarios_Jun2026.docx
B35: H1 FY2026 figures: public SENS / trading update (26 wks to 28 Dec 2025) — not yet catalogued locally; verify.
B36: Macro (oil/rand/rates/fuel/Hormuz): web search, 17 June 2026 — see 'Macro Deck' for dated links.
B38: For informational purposes only — not investment advice. Prepared by internal research from public
B39: disclosures. ZAR. Share prices via web search may be delayed (no live JSE feed). Confirm dealing-period status.

Sheet FY2025 Actuals
B2: SHOPRITE — FY2025 REPORTED ACTUALS (continuing operations)
B3: Reviewed (not audited). FY2024 restated for IFRS 5 (furniture, Ghana, Malawi discontinued). Source: SH1.
B5: Metric | C5: FY2025 | D5: FY2024 (restated) | E5: Change | F5: Source / note
B6: Sale of merchandise | C6: R252.7bn | D6: R232.1bn | E6: +8.9% | F6: SH1, key info
B7: Group revenue | C7: R256.7bn | D7: R236.3bn | E7: +8.6% | F7: SH1, key info
B8: Like-for-like sales | C8: +4.6% | D8: — | E8: — | F8: SH1 (group +4.8%)
B9: Gross profit margin | C9: 24.3% | D9: 23.9% | E9: +40 bps | F9: SH1, gross margin
B10: Trading profit | C10: R15.0bn | D10: — | E10: +16.6% | F10: SH1, trading profit
B11: Trading margin | C11: 5.9% | D11: 5.5% | E11: +40 bps | F11: SH1, trading profit
B12: HEPS (continuing), cents | C12: 1,372.1 | D12: 1,185.3 | E12: +15.8% | F12: SH1, EPS table
B13: Diluted HEPS (continuing), cents | C13: 1,367.2 | D13: 1,180.2 | E13: +15.8% | F13: SH1, key info / EPS
B14: Adjusted DHEPS, cents | C14: 1,410.2 | D14: 1,213.3 | E14: +16.2% | F14: SH1, EPS (pro forma)
B15: DPS total, cents | C15: 781.0 | D15: 712.0 | E15: +9.7% | F15: SH1, dividend decl.
B16: Dividend cover, x | C16: 1.75 | D16: — | E16: policy | F16: SH1, key info
... B24: ROE / ROIC / WACC | C24: 26.7% / 19.4% / 13.5% | D24: — | E24: — | F24: SH1, returns
B26: H1 FY2026 (26 wks to 28 Dec 2025, not yet catalogued locally — verify vs SENS): revenue R138.85bn (+7.1%),
B27: trading profit R7.73bn (+5.9%), diluted HEPS (cont.) 708.9c (+7.9%), interim DPS 307c, Sixty60 R11.9bn (+34.6%).

Sheet Assumptions
A1: SHOPRITE — SCENARIO ASSUMPTIONS
A2: BLUE = input you can change. Forward figures are analyst estimates (e); macro levels are assumptions, not forecasts.
B3: FY2025A | C3: Scenario A — Strait open | E3: Base case | G3: Scenario B — Strait shut
B4: 2025A | C4: 2026e | D4: 2027e | E4: 2026e | F4: 2027e | G4: 2026e | H4: 2027e
A5: Internal selling-price inflation (%) | B5: 0.023 | C5: 0.03 | D5: 0.03 | E5: 0.04 | F5: 0.04 | G5: 0.055 | H5: 0.05
A6: Real volume + space growth (%) | B6: 0.066 | C6: 0.04 | D6: 0.04 | E6: 0.025 | F6: 0.025 | G6: 0.015 | H6: 0.015
A7: Gross margin (%) | B7: 0.243 | C7: 0.243 | D7: 0.244 | E7: 0.242 | F7: 0.242 | G7: 0.24 | H7: 0.239
A8: Trading margin (%) | B8: 0.059 | C8: 0.059 | D8: 0.0595 | E8: 0.0585 | F8: 0.0588 | G8: 0.058 | H8: 0.0572
A9: Net finance costs (R'm) | B9: 4800 | C9: 4700 | D9: 4600 | E9: 4950 | F9: 4900 | G9: 5000 | H9: 5300
A10: Effective tax rate (%) | B10: 0.27 | C10: 0.27 | D10: 0.27 | E10: 0.27 | F10: 0.27 | G10: 0.27 | H10: 0.27
A11: Dividend cover (x) | B11: 1.75 | C11: 1.75 | D11: 1.75 | E11: 1.75 | F11: 1.75 | G11: 1.75 | H11: 1.75
A12: Group rev / sale-of-merch ratio (x) | B12: 1.0158 | C12: 1.0158 | D12: 1.0158 | E12: 1.0158 | F12: 1.0158 | G12: 1.0158 | H12: 1.0158
A13: Effective diluted shares (m) — calibrated (e) | B13: 539.8 | C13: 539.8 | D13: 539.8 | E13: 539.8 | F13: 539.8 | G13: 539.8 | H13: 539.8
A14: Sixty60 sales growth (%) | B14: 0.477 | C14: 0.35 | D14: 0.3 | E14: 0.32 | F14: 0.28 | G14: 0.3 | H14: 0.27
A16: MACRO CONTEXT (analyst scenario assumptions — not forecasts; see 'Macro Deck')
A17: Brent crude (US$/bbl, period avg) | B17: 78 | C17: 72 | D17: 72 | E17: 80 | F17: 78 | G17: 100 | H17: 100
A18: USD/ZAR (period avg) | B18: 18.4 | C18: 16 | D18: 15.8 | E18: 16.5 | F18: 16.8 | G18: 17.5 | H18: 18
A19: SARB repo rate (%, period end) | B19: 0.07 | C19: 0.0667 | D19: 0.0625 | E19: 0.07 | F19: 0.0675 | G19: 0.0817 | H19: 0.0817
A20: Inland 95 petrol (R/l, period end) | B20: 28.06 | C20: 25.5 | D20: 24.5 | E20: 27 | F20: 27 | G20: 29.5 | H20: 30.5
A22: SCENARIO RATIONALE
A23: Scenario A (Strait open): Brent ~$70–80, pump prices ease, food inflation low, SARB resumes cutting, rand firms.
A24: Shoprite's tailwind case — lower diesel/finance costs, volume recovery, room to ease price investment;
A25: HEPS re-accelerates toward low-teens. But a consumer recovery lifts discretionary/premium peers too, so
A26: on a ~20x multiple the share can compound yet LAG a risk-on, cyclical-led rally.
A27: Scenario B (Strait shut): Brent ~$95–110+, pump at/above record, rand weak, SARB tightens (~8.17% severe path).
A28: Tougher business — diesel tailwind reverses with a lag, finance costs climb, volumes soften, margin pressured;
A29: HEPS decelerates to mid/high-single-digit. But this is its relative-strength case: non-discretionary food,
A30: mass-market value leader (Shoprite, Usave), prime trade-down beneficiary, net cash funds price cuts — a
A31: defensive safe-haven that tends to outperform as cyclicals de-rate.

Sheet Scenario Model
A1: SHOPRITE — SCENARIO MODEL (FY2026e–FY2027e)
A2: BLACK = formula • GREEN = link to Assumptions. (e) = analyst estimate. FY2025A is a driver-reproduction of the actuals.
B3: FY2025A | C3: Scenario A — Strait open | E3: Base case | G3: Scenario B — Strait shut
B4: 2025A | C4: 2026e | D4: 2027e | E4: 2026e | F4: 2027e | G4: 2026e | H4: 2027e
A5: Sale-of-merchandise growth (%) | B5: =Assumptions!B5+Assumptions!B6 -> 0.089 | C5: =Assumptions!C5+Assumptions!C6 -> 0.07 | D5: =Assumptions!D5+Assumptions!D6 -> 0.07 | E5: =Assumptions!E5+Assumptions!E6 -> 0.065 | F5: =Assumptions!F5+Assumptions!F6 -> 0.065 | G5: =Assumptions!G5+Assumptions!G6 -> 0.07 | H5: =Assumptions!H5+Assumptions!H6 -> 0.065
A6: Sale of merchandise (R'm) | B6: 252700 | C6: =$B6*(1+C5) -> 270389 | D6: =C6*(1+D5) -> 289316.23 | E6: =$B6*(1+E5) -> 269125.5 | F6: =E6*(1+F5) -> 286618.66 | G6: =$B6*(1+G5) -> 270389 | H6: =G6*(1+H5) -> 287964.28
A7: Group revenue (R'm) (e) | B7: =B6*Assumptions!B12 -> 256692.66 | C7: =C6*Assumptions!C12 -> 274661.15 | D7: =D6*Assumptions!D12 -> 293887.43 | E7: =E6*Assumptions!E12 -> 273377.68 | F7: =F6*Assumptions!F12 -> 291147.23 | G7: =G6*Assumptions!G12 -> 274661.15 | H7: =H6*Assumptions!H12 -> 292514.12
A8: Gross profit (R'm) | B8: =B6*Assumptions!B7 -> 61406.1 | C8: =C6*Assumptions!C7 -> 65704.527 | D8: =D6*Assumptions!D7 -> 70593.16 | E8: =E6*Assumptions!E7 -> 65128.371 | F8: =F6*Assumptions!F7 -> 69361.715 | G8: =G6*Assumptions!G7 -> 64893.36 | H8: =H6*Assumptions!H7 -> 68823.464
A9: Gross margin (%) | B9: =Assumptions!B7 -> 0.243 | C9: =Assumptions!C7 -> 0.243 | D9: =Assumptions!D7 -> 0.244 | E9: =Assumptions!E7 -> 0.242 | F9: =Assumptions!F7 -> 0.242 | G9: =Assumptions!G7 -> 0.24 | H9: =Assumptions!H7 -> 0.239
A10: Trading profit (R'm) | B10: =B6*Assumptions!B8 -> 14909.3 | C10: =C6*Assumptions!C8 -> 15952.951 | D10: =D6*Assumptions!D8 -> 17214.316 | E10: =E6*Assumptions!E8 -> 15743.842 | F10: =F6*Assumptions!F8 -> 16853.177 | G10: =G6*Assumptions!G8 -> 15682.562 | H10: =H6*Assumptions!H8 -> 16471.557
A11: Trading margin (%) | B11: =Assumptions!B8 -> 0.059 | C11: =Assumptions!C8 -> 0.059 | D11: =Assumptions!D8 -> 0.0595 | E11: =Assumptions!E8 -> 0.0585 | F11: =Assumptions!F8 -> 0.0588 | G11: =Assumptions!G8 -> 0.058 | H11: =Assumptions!H8 -> 0.0572
A12: less: Net finance costs (R'm) | B12: =-Assumptions!B9 -> -4800 | C12: =-Assumptions!C9 -> -4700 | D12: =-Assumptions!D9 -> -4600 | E12: =-Assumptions!E9 -> -4950 | F12: =-Assumptions!F9 -> -4900 | G12: =-Assumptions!G9 -> -5000 | H12: =-Assumptions!H9 -> -5300
A13: Profit before tax — proxy (e) | B13: =B10+B12 -> 10109.3 | C13: =C10+C12 -> 11252.951 | D13: =D10+D12 -> 12614.316 | E13: =E10+E12 -> 10793.842 | F13: =F10+F12 -> 11953.177 | G13: =G10+G12 -> 10682.562 | H13: =H10+H12 -> 11171.557
A14: less: Tax at effective rate (e) | B14: =-B13*Assumptions!B10 -> -2729.511 | C14: =-C13*Assumptions!C10 -> -3038.2968 | D14: =-D13*Assumptions!D10 -> -3405.8652 | E14: =-E13*Assumptions!E10 -> -2914.3373 | F14: =-F13*Assumptions!F10 -> -3227.3578 | G14: =-G13*Assumptions!G10 -> -2884.2917 | H14: =-H13*Assumptions!H10 -> -3016.3204
A15: Earnings — proxy (e), R'm | B15: =B13+B14 -> 7379.789 | C15: =C13+C14 -> 8214.6542 | D15: =D13+D14 -> 9208.4505 | E15: =E13+E14 -> 7879.5045 | F15: =F13+F14 -> 8725.8193 | G15: =G13+G14 -> 7798.2703 | H15: =H13+H14 -> 8155.2367
A16: Effective diluted shares (m) | B16: =Assumptions!B13 -> 539.8 | C16: =Assumptions!C13 -> 539.8 | D16: =Assumptions!D13 -> 539.8 | E16: =Assumptions!E13 -> 539.8 | F16: =Assumptions!F13 -> 539.8 | G16: =Assumptions!G13 -> 539.8 | H16: =Assumptions!H13 -> 539.8
A17: Diluted HEPS — proxy (e), cents | B17: =B15/B16*100 -> 1367.1339 | C17: =C15/C16*100 -> 1521.7959 | D17: =D15/D16*100 -> 1705.9004 | E17: =E15/E16*100 -> 1459.7081 | F17: =F15/F16*100 -> 1616.4912 | G17: =G15/G16*100 -> 1444.6592 | H17: =H15/H16*100 -> 1510.7886
A18: HEPS growth (%) | B18: — | C18: =C17/$B17-1 -> 0.1131286 | D18: =D17/C17-1 -> 0.12097846 | E18: =E17/$B17-1 -> 0.06771406 | F18: =F17/E17-1 -> 0.10740711 | G18: =G17/$B17-1 -> 0.056706399 | H18: =H17/G17-1 -> 0.045775077
A19: DPS — total (e), cents | B19: =B17/Assumptions!B11 -> 781.21939 | C19: =C17/Assumptions!C11 -> 869.59765 | D19: =D17/Assumptions!D11 -> 974.80024 | E19: =E17/Assumptions!E11 -> 834.11893 | F19: =F17/Assumptions!F11 -> 923.70923 | G19: =G17/Assumptions!G11 -> 825.51953 | H19: =H17/Assumptions!H11 -> 863.30775
A21: Memo: Sixty60 sales (R'bn) (e) | B21: 18.9 | C21: =$B21*(1+Assumptions!C14) -> 25.515 | D21: =C21*(1+Assumptions!D14) -> 33.1695 | E21: =$B21*(1+Assumptions!E14) -> 24.948 | F21: =E21*(1+Assumptions!F14) -> 31.93344 | G21: =$B21*(1+Assumptions!G14) -> 24.57 | H21: =G21*(1+Assumptions!H14) -> 31.2039
A23: HEPS growth lands: Scenario A ≈ low-teens • Base ≈ mid-to-high single → low-teens • Scenario B ≈ mid/high-single decelerating — matching the briefing.
A24: Relative call: A = good business but may LAG a cyclical rally; B = tougher business but defensive OUTPERFORMER. Neither breaks the case.
A40: Diluted HEPS (e), cents | B40: FY2025A | C40: FY2026e | D40: FY2027e
A41: Scenario A | B41: =B17 -> 1367.1339 | C41: =C17 -> 1521.7959 | D41: =D17 -> 1705.9004
A42: Base | B42: =B17 -> 1367.1339 | C42: =E17 -> 1459.7081 | D42: =F17 -> 1616.4912
A43: Scenario B | B43: =B17 -> 1367.1339 | C43: =G17 -> 1444.6592 | D43: =H17 -> 1510.7886
A45: Trading profit (e), R'm | B45: FY2025A | C45: FY2026e | D45: FY2027e
A46: Scenario A | B46: =B10 -> 14909.3 | C46: =C10 -> 15952.951 | D46: =D10 -> 17214.316
A47: Base | B47: =B10 -> 14909.3 | C47: =E10 -> 15743.842 | D47: =F10 -> 16853.177
A48: Scenario B | B48: =B10 -> 14909.3 | C48: =G10 -> 15682.562 | D48: =H10 -> 16471.557
A50: Trading margin (e), % | B50: FY2025A | C50: FY2026e | D50: FY2027e
A51: Scenario A | B51: =B11 -> 0.059 | C51: =C11 -> 0.059 | D51: =D11 -> 0.0595
A52: Base | B52: =B11 -> 0.059 | C52: =E11 -> 0.0585 | D52: =F11 -> 0.0588
A53: Scenario B | B53: =B11 -> 0.059 | C53: =G11 -> 0.058 | D53: =H11 -> 0.0572

Sheet Macro Deck
B2: MACRO DECK — Strait of Hormuz, oil, rand, rates & fuel (as at 17 June 2026)
B3: Context behind the scenario assumptions. Levels via web search 17 Jun 2026; may be delayed/secondary.
B5: STRAIT OF HORMUZ
B6: Status (17 Jun 2026) | C6: Closed — day ~108 | D6: Largely shut since 28 Feb 2026; straits.live / NBC tracker
B7: Normal vs current transits | C7: ~94/day → ~0/day | D7: NBC News data graphic
B8: Diplomatic track | C8: US & Iran committed to reopen | D8: Bloomberg, 16 Jun 2026
B9: Projected recovery | C9: ~40 transits within 30 days (if holds) | D9: Kpler (via Bloomberg)
B10: Frictions to reopening | C10: War-risk premium ~2.5% hull; mines; stranded ships | D10: Bloomberg, 16 Jun 2026
B12: BRENT CRUDE (US$/bbl)
B13: March 2026 peak | C13: $110+ | D13: Companion note (SH outlook)
B14: 1 June 2026 | C14: $96.42 | D14: Fortune
B15: 15 June 2026 | C15: $84.62 | D15: Fortune
B16: 17 June 2026 (spot) | C16: $79.45 | D16: TradingEconomics
B17: 1-month change | C17: ≈ −29% | D17: TradingEconomics (reopening priced in)
B18: EIA STEO 2026 / 2027 avg | C18: $95 / $79 | D18: EIA STEO, 9 Jun 2026
B20: SOUTH AFRICA — RAND, RATES, FUEL
B21: USD/ZAR (mid-June) | C21: ≈ 16.3 | D21: TradingEconomics / FocusEconomics
B22: SARB repo rate | C22: 7.00% (hiked 25bp 28 May 2026) | D22: First hike in 3 years; oil-shock driven
B23: SARB scenario paths (end-2026) | C23: ~6.67% intermediate / ~8.17% severe | D23: SARB / BusinessTech
B24: Petrol 95 inland (Jun 2026) | C24: Record R28.06/l (+143c) | D24: Incl. fuel-levy relief cut; IOL / gov.za
B25: Diesel (Jun 2026) | C25: Fell: 500ppm R27.92 / 50ppm R28.76 | D25: Levy/slate timing — distribution hit is back-loaded
B26: Fuel-levy relief cut (3–30 Jun) | C26: −R1.50/l petrol, −R1.96/l diesel | D26: gov.za, eff. 3 Jun 2026
B28: Why it matters for Shoprite: petrol = the consumer's wallet; diesel = Shoprite's own distribution cost (FY25 diesel R335m,
B29: down from R810m as load-shedding eased). A sustained closure reverses that tailwind with a lag and lifts finance costs via the SARB.
