Workbook

Sheet Cover
A1: OLD MUTUAL LIMITED (JSE: OMU) — Bull / Bear / Neutral scenario model
B4: Deliverable | C4: FY2026e & FY2027e projected performance under Bull, Neutral (base) and Bear market conditions
B5: Anchor period | C5: FY2025 audited actuals (year ended 31 December 2025); results released 17 March 2026
B6: Base currency | C6: ZAR (R million unless stated; per-share in cents)
B7: Prepared | C7: 18 June 2026 — internal research
B9: Sheet guide
B10: 2. FY2025 Actuals | C10: Sacred reported base — figures verbatim from the FY2025 results booklet
B11: 3. Scenario Drivers | C11: Market-condition assumptions per scenario (analyst estimates, blue = input lever)
B12: 4. FY2026e Model | C12: Projected P&L / KPIs, live formulas off Actuals × Drivers
B13: 5. FY2027e Model | C13: Projected P&L / KPIs, built off FY2026e
B14: 6. Sentiment Scorecard | C14: Management language → tone → earnings / market-share read
B16: Colour key | C16: Black = reported actual (sacred) · Blue = analyst input/estimate (e) · Green = cross-sheet link
B18: For informational purposes only — not investment advice; prepared by internal research from public disclosures (Old Mutual FY2025 Group Annual Results booklet) plus dated macro context. Reported actuals are audited (Deloitte & Touche / EY, unmodified). All FY2026e/FY2027e figures and scenario levels are analyst estimates (e), NOT company guidance. Numbers are sacred: actuals taken verbatim from the cited source.

Sheet FY2025 Actuals
A1: FY2025 reported actuals — the sacred base
A2: Metric | B2: FY2025 | C2: FY2024 | D2: Change | E2: Note
A3: Results from operations (Rm) | B3: 9821 | C3: 8709 | D3: +13% | E3: Operating profit before investment return
A4: Adjusted headline earnings (Rm) | B4: 8263 | C4: 6685 | D4: +24% | E4: Boosted ~R1.9bn by elevated investment returns + Malawi
A5: Adjusted HEPS (cents) | B5: 189.8 | C5: 150.6 | D5: +26%
A6: Headline earnings (Rm) | B6: 8600 | C6: 8800 | D6: -2% | E6: Approx; impacted by Zimbabwe USD transition
A7: HEPS (cents) | B7: 201.6 | C7: 202.7 | D7: -1%
A8: IFRS profit (Rm) | B8: 8400 | C8: 7600 | D8: +10% | E8: Approx; prior yr had China/Nigeria losses
A9: RoNAV reported (%) | B9: 0.152 | C9: 0.127 | D9: +250 bps | E9: Within 15-17% target — flattered by markets
A10: RoNAV normalised (%) | B10: 0.124 | C10: — | D10: n/a | E10: Adjusted for higher-than-expected investment returns
A11: RoNAV excl OM Bank (%) | B11: 0.188 | C11: — | D11: n/a | E11: Old target basis
A12: Return on GEV (%) | B12: 0.041 | C12: — | D12: n/a
A13: Value of new business (Rm) | B13: 850 | C13: 1758 | D13: -52% | E13: Persistency basis strengthening + lower annuity sales
A14: VNB margin (%) | B14: 0.012 | C14: 0.025 | D14: -130 bps | E14: Below 2-3% target
A15: Group equity value / share (c) | B15: 1980.2 | C15: 1950.6 | D15: +2% | E15: R19.80
A16: Total dividend / share (c) | B16: 93 | C16: 86 | D16: +8% | E16: Within 6-9% target; cover 1.5-2.0x
A17: Shareholder solvency ratio (%) | B17: 1.62 | C17: 1.82 | D17: -2000 bps | E17: Within 155-185% target
A18: Gearing ratio (%) | B18: 0.142 | C18: 0.169 | D18: -270 bps | E18: Below 15-20% target — debt capacity
A19: Net client cash flow (Rm) | B19: -10398 | C19: -23227 | D19: +55% | E19: Outflow narrowed materially
A20: Funds under management (Rbn) | B20: 1639 | C20: 1446.9 | D20: +13%
A21: Life APE sales growth (%) | B21: 0.03 | C21: — | D21: +3%
A22: Gross written premiums growth (%) | B22: 0.05 | C22: — | D22: +5% | E22: OM Insure +7%
A23: OM Insure net underwriting margin (%) | B23: 0.068 | C23: 0.062 | D23: +60 bps | E23: Within 5-8% target; 8.3% ex once-off
A25: Cluster RFO (Rm): L&S 7 268 (+13%) · OM Insure 2 062 (+14%) · OM Africa Regions 1 675 (+64%, Malawi) · OM Investments 1 544 (-8%) · OM Bank (1 249) loss · Group activities (1 479).
A26: Source: Old Mutual Group Annual Results for the year ended 31 December 2025 (booklet, released 17 Mar 2026).

Sheet Scenario Drivers
A1: Scenario drivers — market conditions FY2026e / FY2027e (analyst estimates, (e))
A2: Driver | B2: Bull | C2: Neutral | D2: Bear | E2: Rationale
A3: JSE equity market — total return p.a. | B3: 0.18 | C3: 0.09 | D3: -0.06 | E3: Drives investment return, AUM fees, GEV, RoNAV
A4: USD/ZAR (period-avg) | B4: 16 | C4: 17.5 | D4: 19.5 | E4: Rand strength helps translation; weakness hurts
A5: SARB repo rate (period-end, %) | B5: 0.0625 | C5: 0.07 | D5: 0.085 | E5: Higher-for-longer pressures bond values/annuities
A6: Malawi kwacha devaluation | B6: 0 | C6: -0.15 | D6: -0.4 | E6: FY25 flattered by Malawi; mgmt flags 30-50% deval risk
A7: VNB margin achieved (%) | B7: 0.019 | C7: 0.016 | D7: 0.011 | E7: Recovery toward 2-3% target vs 1.2% FY25
A8: Cost savings delivered (Rbn cum.) | B8: 1.2 | C8: 1 | D8: 0.6 | E8: R1bn by FY26 / R2.5bn by FY27 programme
A9: Earnings growth levers applied in the model (analyst (e), blue = input)
A10: Growth lever (YoY) | B10: Bull | C10: Neutral | D10: Bear | E10: Applies to
A11: RFO growth — FY2026e | B11: 0.13 | C11: 0.09 | D11: 0.02 | E11: Results from operations
A12: RFO growth — FY2027e | B12: 0.12 | C12: 0.09 | D12: 0.05 | E12: Results from operations
A13: AHE growth — FY2026e | B13: 0.14 | C13: 0.03 | D13: -0.12 | E13: Adj. headline earnings (market-geared)
A14: AHE growth — FY2027e | B14: 0.13 | C14: 0.08 | D14: 0.04 | E14: Adj. headline earnings
A15: Shares o/s — FY2026e (m) | B15: 4278 | C15: 4290 | D15: 4330 | E15: Buyback pace (R3bn prog., R0.7bn done)
A16: Shares o/s — FY2027e (m) | B16: 4200 | C16: 4230 | D16: 4310 | E16: Buyback pace
A17: DPS growth — FY2026e | B17: 0.09 | C17: 0.07 | D17: 0.03 | E17: Dividend per share
A18: DPS growth — FY2027e | B18: 0.1 | C18: 0.08 | D18: 0.04 | E18: Dividend per share
A19: RoNAV — FY2026e (%) | B19: 0.16 | C19: 0.135 | D19: 0.105 | E19: Return on net asset value
A20: RoNAV — FY2027e (%) | B20: 0.168 | C20: 0.145 | D20: 0.115 | E20: Return on net asset value
A22: Macro levels via web search (Jun 2026): SARB repo 7.00% (hiked 25bp 28 May 2026); USD/ZAR ~16.3-17; SA outlook 'more constructive' per 2026 Budget (mgmt). Levels are analyst scenario assumptions, not guidance.

Sheet FY2026e Model
A1: Projected performance — FY2026 (e)
A2: Metric (FY2026e) | B2: Bull | C2: Neutral | D2: Bear | E2: Basis
A3: Results from operations (Rm) | B3: ='FY2025 Actuals'!B3*(1+'Scenario Drivers'!B11) -> 11097.73 | C3: ='FY2025 Actuals'!B3*(1+'Scenario Drivers'!C11) -> 10704.89 | D3: ='FY2025 Actuals'!B3*(1+'Scenario Drivers'!D11) -> 10017.42 | E3: FY25 RFO × (1+growth lever)
A4: RFO growth (%) | B4: ='Scenario Drivers'!B11 -> 0.13 | C4: ='Scenario Drivers'!C11 -> 0.09 | D4: ='Scenario Drivers'!D11 -> 0.02 | E4: driver
A5: Adjusted headline earnings (Rm) | B5: ='FY2025 Actuals'!B4*(1+'Scenario Drivers'!B13) -> 9419.82 | C5: ='FY2025 Actuals'!B4*(1+'Scenario Drivers'!C13) -> 8510.89 | D5: ='FY2025 Actuals'!B4*(1+'Scenario Drivers'!D13) -> 7271.44 | E5: FY25 AHE × (1+growth lever)
A6: AHE growth (%) | B6: ='Scenario Drivers'!B13 -> 0.14 | C6: ='Scenario Drivers'!C13 -> 0.03 | D6: ='Scenario Drivers'!D13 -> -0.12 | E6: driver — market-geared
A7: Shares outstanding (m) | B7: ='Scenario Drivers'!B15 -> 4278 | C7: ='Scenario Drivers'!C15 -> 4290 | D7: ='Scenario Drivers'!D15 -> 4330 | E7: buyback pace
A8: Adjusted HEPS (cents) | B8: =B5/B7*100 -> 220.19215 | C8: =C5/C7*100 -> 198.38904 | D8: =D5/D7*100 -> 167.93164 | E8: AHE / shares × 100
A9: AHEPS growth vs FY25 (%) | B9: =B8/'FY2025 Actuals'!B5-1 -> 0.16012722 | C9: =C8/'FY2025 Actuals'!B5-1 -> 0.045253131 | D9: =D8/'FY2025 Actuals'!B5-1 -> -0.11521792 | E9: vs 189.8c
A10: Total dividend / share (cents) | B10: ='FY2025 Actuals'!B16*(1+'Scenario Drivers'!B17) -> 101.37 | C10: ='FY2025 Actuals'!B16*(1+'Scenario Drivers'!C17) -> 99.51 | D10: ='FY2025 Actuals'!B16*(1+'Scenario Drivers'!D17) -> 95.79 | E10: FY25 DPS × (1+growth)
A11: RoNAV (%) | B11: ='Scenario Drivers'!B19 -> 0.16 | C11: ='Scenario Drivers'!C19 -> 0.135 | D11: ='Scenario Drivers'!D19 -> 0.105 | E11: vs 15.2% reported / 12.4% norm.
A12: VNB margin (%) | B12: ='Scenario Drivers'!B7 -> 0.019 | C12: ='Scenario Drivers'!C7 -> 0.016 | D12: ='Scenario Drivers'!D7 -> 0.011 | E12: recovery toward 2-3% target
A14: Read | B14: Markets lift investment return & fees; AHE re-accelerates, RoNAV in target band — upgrade trajectory. | C14: Operating momentum (cost savings, Insure, Africa) offset by normalising FY25 investment-return tailwind — earnings broadly flat to modestly up. | D14: Equity selloff + Malawi devaluation reverse the FY25 tailwind; AHE falls though buyback cushions AHEPS — downgrade risk, RoNAV below target.

Sheet FY2027e Model
A1: Projected performance — FY2027 (e)
A2: Metric (FY2027e) | B2: Bull | C2: Neutral | D2: Bear | E2: Basis
A3: Results from operations (Rm) | B3: ='FY2026e Model'!B3*(1+'Scenario Drivers'!B12) -> 12429.458 | C3: ='FY2026e Model'!C3*(1+'Scenario Drivers'!C12) -> 11668.33 | D3: ='FY2026e Model'!D3*(1+'Scenario Drivers'!D12) -> 10518.291 | E3: FY26e RFO × (1+growth)
A4: RFO growth (%) | B4: ='Scenario Drivers'!B12 -> 0.12 | C4: ='Scenario Drivers'!C12 -> 0.09 | D4: ='Scenario Drivers'!D12 -> 0.05 | E4: driver
A5: Adjusted headline earnings (Rm) | B5: ='FY2026e Model'!B5*(1+'Scenario Drivers'!B14) -> 10644.397 | C5: ='FY2026e Model'!C5*(1+'Scenario Drivers'!C14) -> 9191.7612 | D5: ='FY2026e Model'!D5*(1+'Scenario Drivers'!D14) -> 7562.2976 | E5: FY26e AHE × (1+growth)
A6: AHE growth (%) | B6: ='Scenario Drivers'!B14 -> 0.13 | C6: ='Scenario Drivers'!C14 -> 0.08 | D6: ='Scenario Drivers'!D14 -> 0.04 | E6: driver
A7: Shares outstanding (m) | B7: ='Scenario Drivers'!B16 -> 4200 | C7: ='Scenario Drivers'!C16 -> 4230 | D7: ='Scenario Drivers'!D16 -> 4310 | E7: buyback pace
A8: Adjusted HEPS (cents) | B8: =B5/B7*100 -> 253.43801 | C8: =C5/C7*100 -> 217.29932 | D8: =D5/D7*100 -> 175.45934 | E8: AHE / shares × 100
A9: AHEPS growth vs FY25 (%) | B9: =B8/'FY2025 Actuals'!B5-1 -> 0.33528985 | C9: =C8/'FY2025 Actuals'!B5-1 -> 0.14488577 | D9: =D8/'FY2025 Actuals'!B5-1 -> -0.075556686 | E9: 2-yr vs 189.8c
A10: Total dividend / share (cents) | B10: ='FY2026e Model'!B10*(1+'Scenario Drivers'!B18) -> 111.507 | C10: ='FY2026e Model'!C10*(1+'Scenario Drivers'!C18) -> 107.4708 | D10: ='FY2026e Model'!D10*(1+'Scenario Drivers'!D18) -> 99.6216 | E10: FY26e DPS × (1+growth)
A11: RoNAV (%) | B11: ='Scenario Drivers'!B20 -> 0.168 | C11: ='Scenario Drivers'!C20 -> 0.145 | D11: ='Scenario Drivers'!D20 -> 0.115 | E11: approaching 15-17% target
A12: VNB margin (%) | B12: ='Scenario Drivers'!B7+0.004 -> 0.023 | C12: ='Scenario Drivers'!C7+0.004 -> 0.02 | D12: ='Scenario Drivers'!D7+0.004 -> 0.015 | E12: further recovery (e)
A14: Read | B14: Compounding: AHE back above R10bn, RoNAV ~16.8% (mid-target), VNB margin into 2-3% band — clear upgrade case. | C14: Steady delivery: cost programme fully banked, OM Bank loss narrowing toward FY28 break-even, RoNAV ~14.5% (just below target). | D14: Partial recovery off a low base; RoNAV still ~11.5%, below target — value/turnaround story intact but earnings subdued.

Sheet Sentiment Scorecard
A1: Sentiment scorecard — management language → tone → earnings / market-share read
A2: Theme | B2: Management language (verbatim cues) | C2: Tone | D2: Earnings / share read
A3: Overall framing | B3: “Steady operational results in the year of strategic reset and focused execution”; “the focus has now firmly shifted to execution” | C3: Positive | D3: Reset complete; execution-led earnings growth ahead
A4: SA macro outlook | B4: “the South African outlook has become more constructive”; 2026 Budget “reaffirmed a commitment to fiscal discipline”; “more supportive foundation for confidence and investment” | C4: Positive | D4: Supports flows, equity levels, VNB recovery
A5: Global / risk caveat | B5: “the global environment is likely to remain uncertain, shaped by uneven growth and ongoing heightened geopolitical risks” | C5: Negative | D5: Caps the bull case; investment-return volatility
A6: Earnings quality | B6: AHE “further benefitting from elevated shareholder investment returns”; normalised RoNAV 12.4% vs 15.2% reported | C6: Negative | D6: FY25 flattered ~R1.9bn; high normalisation risk in Bear
A7: Malawi | B7: “significantly impacted by elevated returns…in Malawi”; deval of 30-50% would cut AHE growth to 11-16% | C7: Negative | D7: Explicit downside lever to FY26 earnings
A8: Value of new business | B8: VNB “declined by 52%…strengthened persistency assumptions”; margin 1.2% “below our target range” | C8: Negative | D8: Key weak spot; recovery is the swing factor
A9: VNB recovery intent | B9: “We remain committed to restoring our value of new business margin by focusing on…business mix, retention and collections”; “Management actions are on track” | C9: Positive | D9: Credible path back to 2-3% target by FY27
A10: Cost programme | B10: “R2.5 billion commitment…cascaded to cluster scorecards”; “R450 million…already delivered in 2025”; ex-restructuring costs -15% | C10: Positive | D10: Structural margin/earnings support across scenarios
A11: OM Insure | B11: “Continued momentum with margin growth”; net underwriting margin 6.8% (8.3% ex once-off), within 5-8% target | C11: Positive | D11: Reliable RFO growth engine (+14% FY25)
A12: OM Bank | B12: Customer/deposit trends “tracking well, ahead of public marketing campaigns”; profitability targeted FY2028 | C12: Mixed | D12: Loss-making now (-R1.25bn); drag narrows, not gone
A13: Capital / buyback | B13: “R3 billion share buyback…continuing while it remains value accretive”; discretionary capital “almost doubled to R6.1 billion”; gearing below target | C13: Positive | D13: Buyback supports AHEPS/DPS even in Bear
A14: Dividend | B14: Total DPS +8%, “within the medium-term target range”; cover 1.5-2.0x; 3-yr rolling growth 6-9% | C14: Positive | D14: Resilient dividend; smoothed across the cycle
A16: Net sentiment | B16: 7 Positive · 4 Negative · 1 Mixed → NET POSITIVE, but earnings quality and VNB are the genuine negatives that the Bear case crystallises.
