Workbook

Sheet Cover
A1: Shoprite (SHP) vs The SPAR Group (SPP) - Hormuz Scenario Model
A2: Investment Committee working model - internal research, for information only
B4: HOW TO USE THIS MODEL
B5: Change only the BLUE cells on the Assumptions tab. BLACK cells are formulas; GREEN cells link across sheets. Each scenario runs for two forward years against the FY anchor.
B6: Generated by tools/build_model.py from assumptions/<slug>.json + macro/latest.json. Do not hand-edit; re-run the generator.
B8: METHODOLOGY
B9: retail-owned: Sale of merchandise = prior x (1 + selling-price inflation + real volume/space). Trading profit = sales x trading margin. Earnings (e) = trading profit - net finance - tax, over a calibrated effective share count so the FY anchor HEPS ties to the reported figure.
B10: retail-wholesale: Turnover = prior x (1 + growth). Gross & operating profit = turnover x margin. Continuing HEPS (e) is modelled directly off the actual prints (the reported bridge carries large extraordinary/discontinued items); net debt, leverage and finance costs are modelled explicitly because de-gearing is the equity thesis.
B12: FY ANCHORS (reported actuals - sacred)
B13: Shoprite Holdings Limited (SHP) - FY2025A
B14: Sale of merchandise (R'm) | C14: 252700 | E14: SH1 - Shoprite reviewed results, 52 weeks ended 29 June 2025 (FY2024 restated IFRS 5)
B15: Gross margin (%) | C15: 0.243 | E15: SH1 - Shoprite reviewed results, 52 weeks ended 29 June 2025 (FY2024 restated IFRS 5)
B16: Trading margin (%) | C16: 0.059 | E16: SH1 - Shoprite reviewed results, 52 weeks ended 29 June 2025 (FY2024 restated IFRS 5)
B17: Net finance costs (R'm) | C17: 4800 | E17: SH1 - Shoprite reviewed results, 52 weeks ended 29 June 2025 (FY2024 restated IFRS 5)
B18: Diluted HEPS (continuing), c | C18: 1367.2 | E18: SH1 - Shoprite reviewed results, 52 weeks ended 29 June 2025 (FY2024 restated IFRS 5)
B19: Effective diluted shares (m) | C19: 539.8 | E19: SH1 - Shoprite reviewed results, 52 weeks ended 29 June 2025 (FY2024 restated IFRS 5)
B20: Dividend cover (x) | C20: 1.75 | E20: SH1 - Shoprite reviewed results, 52 weeks ended 29 June 2025 (FY2024 restated IFRS 5)
B22: The SPAR Group Limited (SPP) - FY2025A
B23: Turnover (R'm) | C23: 132410 | E23: SP1 - SPAR audited results FY2025 (SENS 8 Dec 2025). H1 FY2026 actual continuing HEPS 199.9c, -55.5% (SP2, published 10 Jun 2026). net_finance_costs_rm is an analyst estimate (e).
B24: Gross margin (%) | C24: 0.108 | E24: SP1 - SPAR audited results FY2025 (SENS 8 Dec 2025). H1 FY2026 actual continuing HEPS 199.9c, -55.5% (SP2, published 10 Jun 2026). net_finance_costs_rm is an analyst estimate (e).
B25: Operating margin ex-extra (%) | C25: 0.021 | E25: SP1 - SPAR audited results FY2025 (SENS 8 Dec 2025). H1 FY2026 actual continuing HEPS 199.9c, -55.5% (SP2, published 10 Jun 2026). net_finance_costs_rm is an analyst estimate (e).
B26: Continuing HEPS, c | C26: 795.8 | E26: SP1 - SPAR audited results FY2025 (SENS 8 Dec 2025). H1 FY2026 actual continuing HEPS 199.9c, -55.5% (SP2, published 10 Jun 2026). net_finance_costs_rm is an analyst estimate (e).
B27: Net debt (R'm) | C27: 5400 | E27: SP1 - SPAR audited results FY2025 (SENS 8 Dec 2025). H1 FY2026 actual continuing HEPS 199.9c, -55.5% (SP2, published 10 Jun 2026). net_finance_costs_rm is an analyst estimate (e).
B28: Net debt leverage (x) | C28: 1.74 | E28: SP1 - SPAR audited results FY2025 (SENS 8 Dec 2025). H1 FY2026 actual continuing HEPS 199.9c, -55.5% (SP2, published 10 Jun 2026). net_finance_costs_rm is an analyst estimate (e).
B29: Shares in issue (m) | C29: 193 | E29: SP1 - SPAR audited results FY2025 (SENS 8 Dec 2025). H1 FY2026 actual continuing HEPS 199.9c, -55.5% (SP2, published 10 Jun 2026). net_finance_costs_rm is an analyst estimate (e).
B31: DISCLAIMER
B32: Numbers are sacred: reported actuals are taken verbatim from the cited source; any figure that is an analyst calculation or projection is marked (e). For informational purposes only — not investment advice; prepared by internal research from public disclosures. Figures reported in ZAR unless stated. Reviewed vs audited status is noted per company. Forward figures and scenario levels are analyst estimates (e), not company guidance. Share/commodity prices via web search may be delayed — there is no live JSE feed here. Confirm the fund's dealing-period status before acting.

Sheet Resilience Scorecard
A1: RESILIENCE SCORECARD - who weathers financial uncertainty better?
A2: Score 1 (most fragile) to 5 (most resilient). Scored primarily for Scenario B (Strait shut) - the stress test. Analyst judgement.
B4: Dimension | C4: SHP | D4: SPP | E4: Why SHP | F4: Why SPP
B5: Balance sheet strength | C5: 5 | D5: 2 | E5: Net CASH R8.1bn; only ~US$7m USD debt. Can fund price cuts & store growth through a downturn. | F5: Net DEBT R5.4bn at 1.74x; de-gearing IS the equity thesis and a high-rate path stalls it.
B6: Earnings momentum entering | C6: 5 | D6: 1 | E6: FY2025 HEPS +15.8%; H1 FY2026 +7.9% - growing into the shock. | F6: H1 FY2026 HEPS -55.5% (199.9c); already in acute distress before any oil shock.
B7: Margin level & direction | C7: 4 | D7: 2 | E7: Trading margin 5.9% and expanding (+40bps); operating leverage intact. | F7: Operating margin halved to 1.1% at H1 (from 2.1%); thin and compressing.
B8: Model under consumer stress | C8: 5 | D8: 2 | E8: Mass-market VALUE leader (Shoprite, Usave) - the prime trade-down WINNER as shoppers downgrade. | F8: Mid-market franchise grocers LOSE share to value chains; trade-down flows away from SPAR.
B9: Distribution / fuel exposure | C9: 4 | D9: 2 | E9: Owned fleet; diesel only R335m in FY2025; scale & efficiency cushion a fuel rise. | F9: Wholesale/distribution model - fuel is core cost-to-serve; KZN DC already wounded; flagged as H2 headwind.
B10: Counterparty / credit risk | C10: 4 | D10: 2 | E10: Largely cash-based retail; limited customer credit exposure. | F10: Finances independent retailers; debtor impairments already rising - a retailer-solvency cycle would bite.
B11: Rand / FX positioning | C11: 3 | D11: 4 | E11: ~85% RSA, minimal FX - little translation upside in a weak-rand world. | F11: Ireland (BWG, EUR1.74bn) is a genuine rand hedge: weak rand flatters euro earnings (~270bps). SPP's one edge.
B12: Management / execution stability | C12: 5 | D12: 2 | E12: Stable, proven team; consistent share-gain track record. | F12: Entire C-suite new since 1 Mar 2026; KZN + SAP execution risk; 61% pay revolt.
B13: Dividend resilience | C13: 5 | D13: 1 | E13: 781c (+9.7%) at 1.75x cover; sustainable through the cycle. | F13: Nil for two straight years; no timeline; FY2026 setback pushes resumption further out.
B14: Valuation cushion | C14: 3 | D14: 3 | E14: Premium ~20x / 2.79% yield - quality, but vulnerable to de-rating if growth stalls. | F14: Cheap (~R60-65, -30% in 90d) but a value-trap risk until the turnaround proves out.
B15: AVERAGE SCORE | C15: =AVERAGE(C5:C14) -> 4.3 | D15: =AVERAGE(D5:D14) -> 2.1 | E15: Shoprite scores higher on every structural axis except FX. | F15: SPAR's only relative edge is the euro (Ireland) rand hedge.
B17: VERDICT
B18: Yes - Shoprite is clearly better positioned than The SPAR Group to weather financial uncertainty, in BOTH scenarios. In Scenario A (Strait open) both improve: Shoprite is a steady compounder that may modestly LAG a cyclical relief rally, while SPAR - geared and distressed - has the higher upside torque IF its self-help (KZN, SAP, cost, retailer loyalty) delivers; that is a higher-risk recovery bet, not resilience. In Scenario B (Strait shut) the gap is widest: Shoprite is a defensive OUTPERFORMER (non-discretionary food, value/trade-down leader, net cash funds a price war), whereas the same oil shock stacks rising rates, a stalled de-gearing, a higher legacy-debt drag, fuel pressure on a distribution-heavy cost base, trade-down OUT of its independents and rising retailer/debtor risk on top of an already-halved margin and a suspended dividend. Own Shoprite for resilience; SPAR is a leveraged recovery option that needs BOTH the macro (A) and execution to go right.

Sheet Macro Deck
A1: MACRO DECK - Strait of Hormuz, oil, rand, rates & fuel (as at 2026-06-17)
A2: Shared scenario context. Levels via web search 17 Jun 2026; may be delayed/secondary. Updated once per run by the analyst, read by both build_model.py and build_note.py.
B4: STRAIT OF HORMUZ
B5: Status (17 Jun 2026) | C5: Closed - day ~108 | D5: straits.live / NBC tracker
B6: Normal vs current transits | C6: ~94/day -> ~0/day | D6: Only ~7 ships since reopening deal; NBC / MarineTraffic
B7: Diplomatic track | C7: US & Iran committed to reopen | D7: Bloomberg, 16 Jun 2026
B8: Frictions to reopening | C8: ~550 ships stranded; mines; war-risk premium ~2.5% hull | D8: Bloomberg / Al Jazeera, 16-17 Jun 2026
B9: BRENT CRUDE (US$/bbl)
B10: March 2026 peak | C10: $110+ | D10: Companion note
B11: 1 June 2026 | C11: $96.42 | D11: Fortune
B12: 17 June 2026 (spot) | C12: ~$79-81 | D12: TradingEconomics / Fortune (reopening priced in)
B13: EIA STEO 2026 / 2027 avg | C13: $95 / $79 | D13: EIA STEO, 9 Jun 2026
B14: SOUTH AFRICA - RAND, RATES, FUEL
B15: USD/ZAR (mid-June) | C15: ~16.3 | D15: TradingEconomics / FocusEconomics
B16: SARB repo rate | C16: 7.00% (hiked 25bp 28 May 2026) | D16: First hike in 3 years; oil-shock driven
B17: SARB scenario paths (end-2026) | C17: ~6.67% intermediate / ~8.17% severe | D17: SARB / BusinessTech
B18: Petrol 95 inland (Jun 2026) | C18: Record R28.06/l | D18: Incl. fuel-levy relief cut; IOL / gov.za
B19: Diesel (Jun 2026) | C19: ~R27.92-28.76 | D19: Levy/slate timing - distribution hit is back-loaded
B21: Why it matters: Petrol = the consumer's wallet (both retailers); diesel = each group's own distribution cost. SPAR is a wholesale-distribution business, so fuel is a larger share of its cost-to-serve; it flagged 'rising fuel costs (logistics/distribution)' as an H2 FY2026 headwind. A sustained closure reverses the diesel tailwind with a lag and lifts finance costs via the SARB - hurting SPAR's net-debt position more than SHP's net-cash one.

Sheet SHP Actuals
A1: Shoprite Holdings Limited - FY ANCHOR (reported actuals)
A2: SACRED - do not edit. Source on Cover. Drives the scenario model.
B4: Metric | C4: FY2025A | D4: Note
B5: Sale of merchandise (R'm) | C5: 252700
B6: Gross margin (%) | C6: 0.243
B7: Trading margin (%) | C7: 0.059
B8: Net finance costs (R'm) | C8: 4800
B9: Diluted HEPS (continuing), c | C9: 1367.2
B10: Effective diluted shares (m) | C10: 539.8
B11: Dividend cover (x) | C11: 1.75
B13: SH1 - Shoprite reviewed results, 52 weeks ended 29 June 2025 (FY2024 restated IFRS 5)

Sheet SPP Actuals
A1: The SPAR Group Limited - FY ANCHOR (reported actuals)
A2: SACRED - do not edit. Source on Cover. Drives the scenario model.
B4: Metric | C4: FY2025A | D4: Note
B5: Turnover (R'm) | C5: 132410
B6: Gross margin (%) | C6: 0.108
B7: Operating margin ex-extra (%) | C7: 0.021
B8: Continuing HEPS, c | C8: 795.8
B9: Net debt (R'm) | C9: 5400
B10: Net debt leverage (x) | C10: 1.74
B11: Shares in issue (m) | C11: 193
B13: SP1 - SPAR audited results FY2025 (SENS 8 Dec 2025). H1 FY2026 actual continuing HEPS 199.9c, -55.5% (SP2, published 10 Jun 2026). net_finance_costs_rm is an analyst estimate (e).

Sheet Assumptions
A1: SCENARIO ASSUMPTIONS
A2: BLUE = input you can change. Forward figures are analyst estimates (e); macro levels are assumptions, not forecasts.
B4: SHARED MACRO (analyst scenario assumptions - see Macro Deck)
C5: FY2025A | D5: A 2026e | E5: A 2027e | F5: Base 2026e | G5: Base 2027e | H5: B 2026e | I5: B 2027e
B6: Brent crude (US$/bbl, period avg) | C6: 78 | D6: 72 | E6: 72 | F6: 80 | G6: 78 | H6: 100 | I6: 100
B7: USD/ZAR (period avg) | C7: 18.4 | D7: 16 | E7: 15.8 | F7: 16.5 | G7: 16.8 | H7: 17.5 | I7: 18
B8: SARB repo rate (%, period end) | C8: 0.07 | D8: 0.0667 | E8: 0.0625 | F8: 0.07 | G8: 0.0675 | H8: 0.0817 | I8: 0.0817
B9: Inland 95 petrol (R/l, period end) | C9: 28.06 | D9: 25.5 | E9: 24.5 | F9: 27 | G9: 27 | H9: 29.5 | I9: 30.5
B11: Shoprite Holdings Limited (SHP) - drivers
C12: FY2025A | D12: A 2026e | E12: A 2027e | F12: Base 2026e | G12: Base 2027e | H12: B 2026e | I12: B 2027e
B13: Internal selling-price inflation (%) | D13: 0.03 | E13: 0.03 | F13: 0.04 | G13: 0.04 | H13: 0.055 | I13: 0.05
B14: Real volume + space growth (%) | D14: 0.04 | E14: 0.04 | F14: 0.025 | G14: 0.025 | H14: 0.015 | I14: 0.015
B15: Gross margin (%) | C15: 0.243 | D15: 0.243 | E15: 0.244 | F15: 0.242 | G15: 0.242 | H15: 0.24 | I15: 0.239
B16: Trading margin (%) | C16: 0.059 | D16: 0.059 | E16: 0.0595 | F16: 0.0585 | G16: 0.0588 | H16: 0.058 | I16: 0.0572
B17: Net finance costs (R'm) | C17: 4800 | D17: 4700 | E17: 4600 | F17: 4950 | G17: 4900 | H17: 5000 | I17: 5300
B18: Effective tax rate (%) | C18: 0.27 | D18: 0.27 | E18: 0.27 | F18: 0.27 | G18: 0.27 | H18: 0.27 | I18: 0.27
B19: Dividend cover (x) | C19: 1.75 | D19: 1.75 | E19: 1.75 | F19: 1.75 | G19: 1.75 | H19: 1.75 | I19: 1.75
B20: Group rev / sale-of-merch ratio (x) | C20: 1.0158 | D20: 1.0158 | E20: 1.0158 | F20: 1.0158 | G20: 1.0158 | H20: 1.0158 | I20: 1.0158
B21: Effective diluted shares (m) | C21: 539.8 | D21: 539.8 | E21: 539.8 | F21: 539.8 | G21: 539.8 | H21: 539.8 | I21: 539.8
B22: Scenario A (Strait open): Brent ~$70-80, pump prices ease, food inflation low, SARB resumes cutting, rand firms. Shoprite's tailwind case - lower diesel/finance costs, volume recovery, room to ease price investment; HEPS re-accelerates toward low-teens, but the share can lag a cyclical relief rally. Scenario B (Strait shut): Brent ~$95-110+, pump at/above record, rand weak, SARB tightens (~8.17% severe path). Tougher business - diesel tailwind reverses with a lag, finance costs climb, volumes soften, margin pressured; HEPS decelerates to mid/high-single-digit. But this is its relative-strength case: non-discretionary food, value leader, prime trade-down beneficiary, net cash funds price cuts.
B24: The SPAR Group Limited (SPP) - drivers
C25: FY2025A | D25: A 2026e | E25: A 2027e | F25: Base 2026e | G25: Base 2027e | H25: B 2026e | I25: B 2027e
B26: Turnover growth (%) | D26: 0.04 | E26: 0.045 | F26: 0.03 | G26: 0.035 | H26: 0.025 | I26: 0.025
B27: Gross margin (%) | C27: 0.108 | D27: 0.109 | E27: 0.11 | F27: 0.108 | G27: 0.109 | H27: 0.106 | I27: 0.106
B28: Operating margin, ex-extraordinary (%) | C28: 0.021 | D28: 0.016 | E28: 0.021 | F28: 0.014 | G28: 0.018 | H28: 0.012 | I28: 0.014
B29: Net finance costs (R'm) (e) | C29: 720 | D29: 620 | E29: 520 | F29: 720 | G29: 650 | H29: 850 | I29: 900
B30: Continuing HEPS (e), cents - anchored on actuals | C30: 795.8 | D30: 470 | E30: 640 | F30: 420 | G30: 540 | H30: 380 | I30: 430
B31: Net debt (R'm) | C31: 5400 | D31: 4700 | E31: 3700 | F31: 5000 | G31: 4400 | H31: 5700 | I31: 5500
B32: Net debt leverage (x) | C32: 1.74 | D32: 1.5 | E32: 1.1 | F32: 1.6 | G32: 1.4 | H32: 1.9 | I32: 1.8
B33: DPS (e), cents | C33: 0 | D33: 0 | E33: 120 | F33: 0 | G33: 60 | H33: 0 | I33: 0
B34: Shares in issue (m) - calibrated (e) | C34: 193 | D34: 193 | E34: 193 | F34: 193 | G34: 193 | H34: 193 | I34: 193
B35: Continuing HEPS is modelled directly off the two ACTUAL prints (FY2025 795.8c; H1 FY2026 199.9c) because SPAR's reported bridge carries large extraordinary/discontinued items. In every scenario FY2026 HEPS sits far below FY2025. Scenario A = de-gearing resumes (lower rates), fuel relief, consumer recovery + self-help (KZN/SAP/cost) lift margin and HEPS - a higher-beta recovery bet, not safety. Scenario B = higher rates stall de-gearing and lift the legacy ZAR-debt drag, fuel hits the distribution-heavy cost base and the wounded KZN DC, trade-down flows OUT of SPAR independents, dividend stays nil.

Sheet SHP Scenario Model
A1: Shoprite Holdings Limited - SCENARIO MODEL
A2: BLACK = formula; GREEN = link to Assumptions. (e) = analyst estimate. FY anchor reproduces reported actuals.
B4: R'm unless stated | C4: FY2025A | D4: A 2026e | E4: A 2027e | F4: Base 2026e | G4: Base 2027e | H4: B 2026e | I4: B 2027e
B5: Sale of merchandise | C5: 252700 | D5: =C5*(1+Assumptions!$D$13+Assumptions!$D$14) -> 270389 | E5: =D5*(1+Assumptions!$E$13+Assumptions!$E$14) -> 289316.23 | F5: =C5*(1+Assumptions!$F$13+Assumptions!$F$14) -> 269125.5 | G5: =F5*(1+Assumptions!$G$13+Assumptions!$G$14) -> 286618.66 | H5: =C5*(1+Assumptions!$H$13+Assumptions!$H$14) -> 270389 | I5: =H5*(1+Assumptions!$I$13+Assumptions!$I$14) -> 287964.28
B6: Group revenue (e) | C6: =C5*Assumptions!$C$20 -> 256692.66 | D6: =D5*Assumptions!$D$20 -> 274661.15 | E6: =E5*Assumptions!$E$20 -> 293887.43 | F6: =F5*Assumptions!$F$20 -> 273377.68 | G6: =G5*Assumptions!$G$20 -> 291147.23 | H6: =H5*Assumptions!$H$20 -> 274661.15 | I6: =I5*Assumptions!$I$20 -> 292514.12
B7: Gross profit | C7: =C5*Assumptions!$C$15 -> 61406.1 | D7: =D5*Assumptions!$D$15 -> 65704.527 | E7: =E5*Assumptions!$E$15 -> 70593.16 | F7: =F5*Assumptions!$F$15 -> 65128.371 | G7: =G5*Assumptions!$G$15 -> 69361.715 | H7: =H5*Assumptions!$H$15 -> 64893.36 | I7: =I5*Assumptions!$I$15 -> 68823.464
B8: Gross margin (%) | C8: =C7/C5 -> 0.243 | D8: =D7/D5 -> 0.243 | E8: =E7/E5 -> 0.244 | F8: =F7/F5 -> 0.242 | G8: =G7/G5 -> 0.242 | H8: =H7/H5 -> 0.24 | I8: =I7/I5 -> 0.239
B9: Trading profit | C9: =C5*Assumptions!$C$16 -> 14909.3 | D9: =D5*Assumptions!$D$16 -> 15952.951 | E9: =E5*Assumptions!$E$16 -> 17214.316 | F9: =F5*Assumptions!$F$16 -> 15743.842 | G9: =G5*Assumptions!$G$16 -> 16853.177 | H9: =H5*Assumptions!$H$16 -> 15682.562 | I9: =I5*Assumptions!$I$16 -> 16471.557
B10: Trading margin (%) | C10: =C9/C5 -> 0.059 | D10: =D9/D5 -> 0.059 | E10: =E9/E5 -> 0.0595 | F10: =F9/F5 -> 0.0585 | G10: =G9/G5 -> 0.0588 | H10: =H9/H5 -> 0.058 | I10: =I9/I5 -> 0.0572
B11: less: Net finance costs | C11: =-Assumptions!$C$17 -> -4800 | D11: =-Assumptions!$D$17 -> -4700 | E11: =-Assumptions!$E$17 -> -4600 | F11: =-Assumptions!$F$17 -> -4950 | G11: =-Assumptions!$G$17 -> -4900 | H11: =-Assumptions!$H$17 -> -5000 | I11: =-Assumptions!$I$17 -> -5300
B12: Profit before tax - proxy (e) | C12: =C9+C11 -> 10109.3 | D12: =D9+D11 -> 11252.951 | E12: =E9+E11 -> 12614.316 | F12: =F9+F11 -> 10793.842 | G12: =G9+G11 -> 11953.177 | H12: =H9+H11 -> 10682.562 | I12: =I9+I11 -> 11171.557
B13: less: Tax (e) | C13: =-C12*Assumptions!$C$18 -> -2729.511 | D13: =-D12*Assumptions!$D$18 -> -3038.2968 | E13: =-E12*Assumptions!$E$18 -> -3405.8652 | F13: =-F12*Assumptions!$F$18 -> -2914.3373 | G13: =-G12*Assumptions!$G$18 -> -3227.3578 | H13: =-H12*Assumptions!$H$18 -> -2884.2917 | I13: =-I12*Assumptions!$I$18 -> -3016.3204
B14: Earnings - proxy (e) | C14: =C12+C13 -> 7379.789 | D14: =D12+D13 -> 8214.6542 | E14: =E12+E13 -> 9208.4505 | F14: =F12+F13 -> 7879.5045 | G14: =G12+G13 -> 8725.8193 | H14: =H12+H13 -> 7798.2703 | I14: =I12+I13 -> 8155.2367
B15: Diluted HEPS - proxy (e), cents | C15: =C14/Assumptions!$C$21*100 -> 1367.1339 | D15: =D14/Assumptions!$D$21*100 -> 1521.7959 | E15: =E14/Assumptions!$E$21*100 -> 1705.9004 | F15: =F14/Assumptions!$F$21*100 -> 1459.7081 | G15: =G14/Assumptions!$G$21*100 -> 1616.4912 | H15: =H14/Assumptions!$H$21*100 -> 1444.6592 | I15: =I14/Assumptions!$I$21*100 -> 1510.7886
B16: HEPS growth (%) | C16: - | D16: =D15/C15-1 -> 0.1131286 | E16: =E15/D15-1 -> 0.12097846 | F16: =F15/C15-1 -> 0.06771406 | G16: =G15/F15-1 -> 0.10740711 | H16: =H15/C15-1 -> 0.056706399 | I16: =I15/H15-1 -> 0.045775077
B17: DPS - total (e), cents | C17: =C15/Assumptions!$C$19 -> 781.21939 | D17: =D15/Assumptions!$D$19 -> 869.59765 | E17: =E15/Assumptions!$E$19 -> 974.80024 | F17: =F15/Assumptions!$F$19 -> 834.11893 | G17: =G15/Assumptions!$G$19 -> 923.70923 | H17: =H15/Assumptions!$H$19 -> 825.51953 | I17: =I15/Assumptions!$I$19 -> 863.30775

Sheet SPP Scenario Model
A1: The SPAR Group Limited - SCENARIO MODEL
A2: BLACK = formula; GREEN = link to Assumptions. (e) = analyst estimate. FY anchor reproduces reported actuals.
B4: R'm unless stated | C4: FY2025A | D4: A 2026e | E4: A 2027e | F4: Base 2026e | G4: Base 2027e | H4: B 2026e | I4: B 2027e
B5: Turnover (continuing) | C5: 132410 | D5: =C5*(1+Assumptions!$D$26) -> 137706.4 | E5: =D5*(1+Assumptions!$E$26) -> 143903.19 | F5: =C5*(1+Assumptions!$F$26) -> 136382.3 | G5: =F5*(1+Assumptions!$G$26) -> 141155.68 | H5: =C5*(1+Assumptions!$H$26) -> 135720.25 | I5: =H5*(1+Assumptions!$I$26) -> 139113.26
B6: Turnover growth (%) | C6: - | D6: =D5/C5-1 -> 0.04 | E6: =E5/D5-1 -> 0.045 | F6: =F5/C5-1 -> 0.03 | G6: =G5/F5-1 -> 0.035 | H6: =H5/C5-1 -> 0.025 | I6: =I5/H5-1 -> 0.025
B7: Gross profit | C7: =C5*Assumptions!$C$27 -> 14300.28 | D7: =D5*Assumptions!$D$27 -> 15009.998 | E7: =E5*Assumptions!$E$27 -> 15829.351 | F7: =F5*Assumptions!$F$27 -> 14729.288 | G7: =G5*Assumptions!$G$27 -> 15385.969 | H7: =H5*Assumptions!$H$27 -> 14386.346 | I7: =I5*Assumptions!$I$27 -> 14746.005
B8: Operating profit (ex-extraordinary) | C8: =C5*Assumptions!$C$28 -> 2780.61 | D8: =D5*Assumptions!$D$28 -> 2203.3024 | E8: =E5*Assumptions!$E$28 -> 3021.9669 | F8: =F5*Assumptions!$F$28 -> 1909.3522 | G8: =G5*Assumptions!$G$28 -> 2540.8022 | H8: =H5*Assumptions!$H$28 -> 1628.643 | I8: =I5*Assumptions!$I$28 -> 1947.5856
B9: Operating margin (%) | C9: =Assumptions!$C$28 -> 0.021 | D9: =Assumptions!$D$28 -> 0.016 | E9: =Assumptions!$E$28 -> 0.021 | F9: =Assumptions!$F$28 -> 0.014 | G9: =Assumptions!$G$28 -> 0.018 | H9: =Assumptions!$H$28 -> 0.012 | I9: =Assumptions!$I$28 -> 0.014
B10: less: Net finance costs (e) | C10: =-Assumptions!$C$29 -> -720 | D10: =-Assumptions!$D$29 -> -620 | E10: =-Assumptions!$E$29 -> -520 | F10: =-Assumptions!$F$29 -> -720 | G10: =-Assumptions!$G$29 -> -650 | H10: =-Assumptions!$H$29 -> -850 | I10: =-Assumptions!$I$29 -> -900
B11: Continuing HEPS (e), cents | C11: =Assumptions!$C$30 -> 795.8 | D11: =Assumptions!$D$30 -> 470 | E11: =Assumptions!$E$30 -> 640 | F11: =Assumptions!$F$30 -> 420 | G11: =Assumptions!$G$30 -> 540 | H11: =Assumptions!$H$30 -> 380 | I11: =Assumptions!$I$30 -> 430
B12: HEPS growth (%) | C12: - | D12: =D11/C11-1 -> -0.40939935 | E12: =E11/D11-1 -> 0.36170213 | F12: =F11/C11-1 -> -0.4722292 | G12: =G11/F11-1 -> 0.28571429 | H12: =H11/C11-1 -> -0.52249309 | I12: =I11/H11-1 -> 0.13157895
B13: Implied cont. headline earnings (memo) | C13: =C11*Assumptions!$C$34/100 -> 1535.894 | D13: =D11*Assumptions!$D$34/100 -> 907.1 | E13: =E11*Assumptions!$E$34/100 -> 1235.2 | F13: =F11*Assumptions!$F$34/100 -> 810.6 | G13: =G11*Assumptions!$G$34/100 -> 1042.2 | H13: =H11*Assumptions!$H$34/100 -> 733.4 | I13: =I11*Assumptions!$I$34/100 -> 829.9
B14: Net debt | C14: =Assumptions!$C$31 -> 5400 | D14: =Assumptions!$D$31 -> 4700 | E14: =Assumptions!$E$31 -> 3700 | F14: =Assumptions!$F$31 -> 5000 | G14: =Assumptions!$G$31 -> 4400 | H14: =Assumptions!$H$31 -> 5700 | I14: =Assumptions!$I$31 -> 5500
B15: Net debt leverage (x) | C15: =Assumptions!$C$32 -> 1.74 | D15: =Assumptions!$D$32 -> 1.5 | E15: =Assumptions!$E$32 -> 1.1 | F15: =Assumptions!$F$32 -> 1.6 | G15: =Assumptions!$G$32 -> 1.4 | H15: =Assumptions!$H$32 -> 1.9 | I15: =Assumptions!$I$32 -> 1.8
B16: DPS (e), cents | C16: =Assumptions!$C$33 -> 0 | D16: =Assumptions!$D$33 -> 0 | E16: =Assumptions!$E$33 -> 120 | F16: =Assumptions!$F$33 -> 0 | G16: =Assumptions!$G$33 -> 60 | H16: =Assumptions!$H$33 -> 0 | I16: =Assumptions!$I$33 -> 0
