Workbook

Sheet Cover & Sources
B2: GOLD FIELDS LIMITED (JSE: GFI • NYSE: GFI)
B3: Companion scenario model — 12–18 month outlook under Strait-of-Hormuz scenarios
B4: Investment Committee working model • 17 June 2026 • Reporting currency: US$ (Dec year-end)
B6: HOW TO USE THIS MODEL
B7: • Change only the BLUE cells on the 'Assumptions' tab. Every output on 'Scenario Model' re-runs automatically.
B8: • The 'Growth Scorecard' tab tracks the company-specific growth catalysts (Salares Norte, Windfall FID, reserves,
B9: AISC, Tarkwa) with a quarterly RAG check — update the quarter columns each results cycle.
B10: • Three scenarios run side by side: Scenario A (Strait of Hormuz remains open / peace holds), a Base case,
B11: and Scenario B (Hormuz closes again and stays closed). FY2025A is the actual, used to calibrate the method.
B12: • Volume is held near company guidance (2.40–2.60 Moz attributable) across scenarios to isolate the gold-price
B13: and cost channels — the two levers the Hormuz outcome actually moves for a gold producer.
B15: METHODOLOGY (transparent, calibrated to FY2025 actuals):
... B26: KEY SOURCES
B27: • Gold Fields FY2025 reviewed results (SEC Form 6-K) | E27: sec.gov EDGAR CIK 1172724, filed 19–20 Feb 2026
B28: • Gold Fields Q1 2026 operational update (SEC Form 6-K) | E28: filed 7 May 2026 — FY2026 guidance reaffirmed
B29: • Gold Fields 2025 Integrated Annual Report / GRR | E29: goldfields.com/investors (risks & remuneration)
B30: • Gold price / spot & records | E30: Fortune, CBS, J.P. Morgan, WGC — Jan ATH ~US$5,589; mid-Jun ~US$4,340/oz
B31: • Gold forecasts | E31: JPM YE US$6,000; BofA US$6,000; Goldman US$5,400; World Bank avg US$4,700 (2026)
B32: • Brent / Hormuz | E32: CNN, Fortune, World Bank CMO Apr-2026; Citi US$150, Macquarie US$200 (extended-closure)
B33: • Oil→AISC transmission | E33: Jefferies (Northern Miner, Jun-2026): +US$20–30/bbl ≈ +US$85–160/oz AISC
B35: For informational purposes only; not investment advice. Prices obtained via search may be delayed; no live JSE/COMEX feed. (e) = analyst estimate.

Sheet Growth Scorecard
A1: GOLD FIELDS — GROWTH SCORECARD (next 12–18 months)
A2: Company-specific growth catalysts. RAG: Green on-track / Amber watch / Red behind / Grey pending. Update the quarter columns each results cycle. (Macro/scenario indicators live on 'Scenario Model' & 'Macro Deck'.)
A4: Growth indicator | B4: On-track signal / threshold | C4: FY2025A | D4: FY2026 guidance / target | E4: Latest read (Q1 2026) | F4: Q2'26 | G4: Q3'26 | H4: Q4'26 | I4: 1H'27
A5: Production & project delivery
A6: Salares Norte run-rate | B6: at least 525koz @ AISC <US$600/oz | C6: 397koz @ $1,144 | D6: 525-550koz @ ~$450-600/oz | E6: 173koz Q1; AIC ~$165/oz — ahead
A7: Windfall (Canada) FID | B7: Sanctioned mid-2026 on-plan; reserves updated | C7: Pre-FID (acq. 2024) | D7: FID + district feasibility/reserves | E7: EIA hearings done; Cree IBA in principle
A8: Group attributable production | B8: at least 2.50Moz (mid-upper of guidance) | C8: 2.438Moz | D8: 2.40-2.60Moz | E8: 633koz Q1 (+15% YoY) — on track
A9: Margin & cash growth
A10: Group AISC | B10: at or below US$1,900/oz (mid-guidance) | C10: US$1,645/oz | D10: US$1,800-2,000/oz | E10: US$1,829 Q1 (FX headwind) — watch
A11: Adjusted free cash flow | B11: Grow despite the capex step-up | C11: US$2,970m | D11: capex US$1.9-2.1bn | E11: Net debt US$1,304m post-dividend
A12: Net debt / adj. EBITDA | B12: below 0.5x through the cycle | C12: 0.26x | D12: — | E12: 0.19x Q1 — strong
A13: Structural / pipeline growth
A14: Reserve & resource replacement | B14: Replacement >100%; district additions | C14: Annual SAMREC declaration | D14: 2025 IAR + Windfall update | E14: Pending annual declaration
A15: Cerro Corona life extension | B15: LOM extended toward ~2040 | C15: Studies underway | D15: Nueva Esperanza exploration | E15: Studies ongoing — pending
A16: Jurisdictional gates
A17: Tarkwa lease renewal | B17: Renewed on workable terms (exp. Apr 2027) | C17: ~470koz at stake | D17: Renewal application in process | E17: 'Not automatic'; new royalty regime — watch
A18: Australian recovery (Gruyere/Agnew) | B18: H2-2026 normalisation | C18: — | D18: Recovery plans in place | E18: Gruyere -25%, Agnew seismic Q1 — watch
A20: Legend: | B20: On-track | C20: Watch | D20: Behind | E20: Pending
A22: For informational purposes only; not investment advice. Latest read = Q1 2026 operational update (7 May 2026). Group volume growth is broadly flat in 2026 (Salares Norte offsets the Damang handover and Cerro Corona's move to stockpiles); the genuine growth is margin/FCF and the de-risking pipeline (Windfall FID, reserves).

Sheet Assumptions
A1: GOLD FIELDS — SCENARIO ASSUMPTIONS (edit BLUE cells)
A2: All forward figures are analyst estimates (e). FY2025A = reported actual (calibration).
B3: FY2025A | C3: Scenario A — Hormuz open | E3: Base | G3: Scenario B — Hormuz closed
B4: 2025A | C4: 2026e | D4: 2027e | E4: 2026e | F4: 2027e | G4: 2026e | H4: 2027e
A5: Realised gold price (US$/oz) | B5: 3496 | C5: 4400 | D5: 4700 | E5: 4500 | F5: 5000 | G5: 4900 | H5: 5400
A6: Attributable production (Moz) | B6: 2.438 | C6: 2.5 | D6: 2.55 | E6: 2.5 | F6: 2.55 | G6: 2.48 | H6: 2.52
A7: AISC — all-in sustaining cost (US$/oz) | B7: 1645 | C7: 1850 | D7: 1800 | E7: 1900 | F7: 1900 | G7: 2000 | H7: 2050
A8: AIC — all-in cost (US$/oz) | B8: 1927 | C8: 2150 | D8: 2050 | E8: 2200 | F8: 2150 | G8: 2300 | H8: 2350
A9: Sustaining capex (US$m) | B9: 1029 | C9: 1350 | D9: 1300 | E9: 1350 | F9: 1300 | G9: 1380 | H9: 1330
A10: Effective cash tax rate (%) | B10: 0.31 | C10: 0.3 | D10: 0.3 | E10: 0.3 | F10: 0.3 | G10: 0.3 | H10: 0.3
A11: Shareholder payout (% of FCF proxy) | B11: 0.54 | C11: 0.45 | D11: 0.45 | E11: 0.45 | F11: 0.45 | G11: 0.4 | H11: 0.4
A12: USD/ZAR (period average) | B12: 18.3 | C12: 18 | D12: 17.8 | E12: 18.5 | F12: 18.5 | G12: 19.5 | H12: 19.8
A14: SCENARIO RATIONALE (estimates):
A15: Scenario A (Hormuz open): MOU holds, Brent normalises ~US$70–80. Energy inflation fades, the Fed resumes
A16: easing → lower real rates support gold's structural bull (CB buying, debasement). Safe-haven premium fades;
A17: gold consolidates ~US$4,400 then firms. AISC eases toward mid-guidance as diesel falls.
A18: Scenario B (Hormuz closed): Brent spikes (Citi US$150 / Macquarie US$200). Stagflation + geopolitical +
A19: debasement push gold to re-test/exceed its Jan-2026 record (~US$5,589). BUT energy-driven inflation keeps
A20: the Fed hawkish (real-rate headwind, as in Mar-2026) → higher gold with far greater volatility. AISC rises
A21: on diesel/consumables (Jefferies: +US$20–30/bbl ≈ +US$85–160/oz), partly offset by a weaker ZAR/AUD (USD-cost
A22: tailwind for a US$ reporter). Base case sits between the two.

Sheet Scenario Model
A1: GOLD FIELDS — SCENARIO MODEL OUTPUT (US$m unless stated)
A2: Black = formula • Green = link to Assumptions. Outputs re-run when blue inputs change.
B3: FY2025A | C3: Scenario A — Hormuz open | E3: Base | G3: Scenario B — Hormuz closed
B4: 2025A | C4: 2026e | D4: 2027e | E4: 2026e | F4: 2027e | G4: 2026e | H4: 2027e
A5: Realised gold price (US$/oz) | B5: =Assumptions!B5 -> 3496 | C5: =Assumptions!C5 -> 4400 | D5: =Assumptions!D5 -> 4700 | E5: =Assumptions!E5 -> 4500 | F5: =Assumptions!F5 -> 5000 | G5: =Assumptions!G5 -> 4900 | H5: =Assumptions!H5 -> 5400
A6: Attributable production (Moz) | B6: =Assumptions!B6 -> 2.438 | C6: =Assumptions!C6 -> 2.5 | D6: =Assumptions!D6 -> 2.55 | E6: =Assumptions!E6 -> 2.5 | F6: =Assumptions!F6 -> 2.55 | G6: =Assumptions!G6 -> 2.48 | H6: =Assumptions!H6 -> 2.52
A7: AISC (US$/oz) | B7: =Assumptions!B7 -> 1645 | C7: =Assumptions!C7 -> 1850 | D7: =Assumptions!D7 -> 1800 | E7: =Assumptions!E7 -> 1900 | F7: =Assumptions!F7 -> 1900 | G7: =Assumptions!G7 -> 2000 | H7: =Assumptions!H7 -> 2050
A8: AIC (US$/oz) | B8: =Assumptions!B8 -> 1927 | C8: =Assumptions!C8 -> 2150 | D8: =Assumptions!D8 -> 2050 | E8: =Assumptions!E8 -> 2200 | F8: =Assumptions!F8 -> 2150 | G8: =Assumptions!G8 -> 2300 | H8: =Assumptions!H8 -> 2350
A10: Revenue | B10: =B5*B6 -> 8523.248 | C10: =C5*C6 -> 11000 | D10: =D5*D6 -> 11985 | E10: =E5*E6 -> 11250 | F10: =F5*F6 -> 12750 | G10: =G5*G6 -> 12152 | H10: =H5*H6 -> 13608
A11: less: AISC cash cost | B11: =-B7*B6 -> -4010.51 | C11: =-C7*C6 -> -4625 | D11: =-D7*D6 -> -4590 | E11: =-E7*E6 -> -4750 | F11: =-F7*F6 -> -4845 | G11: =-G7*G6 -> -4960 | H11: =-H7*H6 -> -5166
A12: Group AISC margin | B12: =B10+B11 -> 4512.738 | C12: =C10+C11 -> 6375 | D12: =D10+D11 -> 7395 | E12: =E10+E11 -> 6500 | F12: =F10+F11 -> 7905 | G12: =G10+G11 -> 7192 | H12: =H10+H11 -> 8442
A13: add: sustaining capex | B13: =Assumptions!B9 -> 1029 | C13: =Assumptions!C9 -> 1350 | D13: =Assumptions!D9 -> 1300 | E13: =Assumptions!E9 -> 1350 | F13: =Assumptions!F9 -> 1300 | G13: =Assumptions!G9 -> 1380 | H13: =Assumptions!H9 -> 1330
A14: EBITDA (e) | B14: =B12+B13 -> 5541.738 | C14: =C12+C13 -> 7725 | D14: =D12+D13 -> 8695 | E14: =E12+E13 -> 7850 | F14: =F12+F13 -> 9205 | G14: =G12+G13 -> 8572 | H14: =H12+H13 -> 9772
A15: EBITDA margin (%) | B15: =B14/B10 -> 0.65019087 | C15: =C14/C10 -> 0.70227273 | D15: =D14/D10 -> 0.7254902 | E15: =E14/E10 -> 0.69777778 | F15: =F14/F10 -> 0.72196078 | G15: =G14/G10 -> 0.70539829 | H15: =H14/H10 -> 0.718107
A17: All-in margin, pre-tax | B17: =B10-B8*B6 -> 3825.222 | C17: =C10-C8*C6 -> 5625 | D17: =D10-D8*D6 -> 6757.5 | E17: =E10-E8*E6 -> 5750 | F17: =F10-F8*F6 -> 7267.5 | G17: =G10-G8*G6 -> 6448 | H17: =H10-H8*H6 -> 7686
A18: less: cash tax (e) | B18: =-B17*Assumptions!B10 -> -1185.8188 | C18: =-C17*Assumptions!C10 -> -1687.5 | D18: =-D17*Assumptions!D10 -> -2027.25 | E18: =-E17*Assumptions!E10 -> -1725 | F18: =-F17*Assumptions!F10 -> -2180.25 | G18: =-G17*Assumptions!G10 -> -1934.4 | H18: =-H17*Assumptions!H10 -> -2305.8
A19: Post-tax all-in FCF proxy (e) | B19: =B17+B18 -> 2639.4032 | C19: =C17+C18 -> 3937.5 | D19: =D17+D18 -> 4730.25 | E19: =E17+E18 -> 4025 | F19: =F17+F18 -> 5087.25 | G19: =G17+G18 -> 4513.6 | H19: =H17+H18 -> 5380.2
A20: Implied shareholder returns (e) | B20: =B19*Assumptions!B11 -> 1425.2777 | C20: =C19*Assumptions!C11 -> 1771.875 | D20: =D19*Assumptions!D11 -> 2128.6125 | E20: =E19*Assumptions!E11 -> 1811.25 | F20: =F19*Assumptions!F11 -> 2289.2625 | G20: =G19*Assumptions!G11 -> 1805.44 | H20: =H19*Assumptions!H11 -> 2152.08
A22: Memo: Revenue (ZAR bn) | B22: =B10*Assumptions!B12/1000 -> 155.97544 | C22: =C10*Assumptions!C12/1000 -> 198 | D22: =D10*Assumptions!D12/1000 -> 213.333 | E22: =E10*Assumptions!E12/1000 -> 208.125 | F22: =F10*Assumptions!F12/1000 -> 235.875 | G22: =G10*Assumptions!G12/1000 -> 236.964 | H22: =H10*Assumptions!H12/1000 -> 269.4384
A23: Memo: EBITDA (ZAR bn) | B23: =B14*Assumptions!B12/1000 -> 101.41381 | C23: =C14*Assumptions!C12/1000 -> 139.05 | D23: =D14*Assumptions!D12/1000 -> 154.771 | E23: =E14*Assumptions!E12/1000 -> 145.225 | F23: =F14*Assumptions!F12/1000 -> 170.2925 | G23: =G14*Assumptions!G12/1000 -> 167.154 | H23: =H14*Assumptions!H12/1000 -> 193.4856
A25: EBITDA vs FY2025A (%) | B25: — | C25: =C14/$B$14-1 -> 0.39396702 | D25: =D14/$B$14-1 -> 0.56900236 | E25: =E14/$B$14-1 -> 0.41652312 | F25: =F14/$B$14-1 -> 0.66103125 | G25: =G14/$B$14-1 -> 0.54680716 | H25: =H14/$B$14-1 -> 0.76334572
A26: FCF proxy vs FY2025A (%) | B26: — | C26: =C19/$B$19-1 -> 0.49181452 | D26: =D19/$B$19-1 -> 0.79216652 | E26: =E19/$B$19-1 -> 0.52496596 | F26: =F19/$B$19-1 -> 0.92742437 | G26: =G19/$B$19-1 -> 0.71008357 | H26: =H19/$B$19-1 -> 1.0384154
A29: SUMMARY — EBITDA (e), US$m
B30: 2026e | C30: 2027e
A31: Scenario A — Hormuz open | B31: =C14 -> 7725 | C31: =D14 -> 8695
A32: Base | B32: =E14 -> 7850 | C32: =F14 -> 9205
A33: Scenario B — Hormuz closed | B33: =G14 -> 8572 | C33: =H14 -> 9772
A45: SENSITIVITY (rule of thumb, at ~2.50 Moz)
A46: EBITDA / FCF impact per +US$100/oz on the gold price | B46: =100*$E$6 -> 250 | C46: US$m
A47: EBITDA impact per +US$100/oz on AISC | B47: =-100*$E$6 -> -250 | C47: US$m
A49: For informational purposes only; not investment advice. (e) = analyst estimate.

Sheet Macro Deck
A1: MACRO DECK — gold & Brent reference (mid-June 2026)
A3: GOLD (US$/oz)
A4: 2026 record high (28–29 Jan) | B4: ~5,589 spot / 5,542 futures | C4: CBS / aggregators
A5: Pre-war retreat (early Feb) | B5: ~4,099
A6: Iran strikes begin (1 Mar) | B6: ~5,246
A7: Intra-year floor (Jun) | B7: ~4,170 | C7: J.P. Morgan, 9 Jun
A8: Spot today (17 Jun) | B8: ~4,340–4,350 | C8: Fortune / TradingEconomics
A9: JPMorgan 2026 avg / YE | B9: 5,243 / 6,000 | C9: 9 Jun 2026
A10: BofA 12-month target | B10: 6,000 | C10: 1 May 2026
A11: Goldman year-end | B11: 5,400 | C11: reaffirmed Apr 2026
A12: World Bank 2026 avg | B12: ~4,700 | C12: CMO Apr 2026
A14: BRENT (US$/bbl)
A15: Pre-war | B15: ~73
A16: Intraday peak (30 Apr) | B16: 126 (thin) / 114 close | C16: CNN / CNBC
A17: Today (17 Jun) | B17: ~79–82 | C17: Fortune / TradingEconomics
A18: Citi — extended closure | B18: ~150 (avg ~130 Q2–Q3) | C18: 26 Apr 2026
A19: Macquarie — war persists | B19: up to 200 | C19: 27 Mar 2026
A20: BlackRock (Fink) | B20: ~150 even w/ ceasefire | C20: 25 Mar 2026
A21: World Bank upside | B21: 95–115 (2026) | C21: CMO Apr 2026
A22: EIA 2026 / 2027 avg | B22: 95 / 79 | C22: STEO 9 Jun 2026
A24: Strait of Hormuz (17 Jun 2026): effectively closed to open commercial traffic; US–Iran MOU announced 14 Jun, signing set 19 Jun (Geneva).
A25: Tolling dispute live: US says toll-free & permanent; IRGC-linked Fars says toll-free 60 days only. Ceasefire repeatedly violated during the war.

Sheet FY2025 Actuals
A1: GOLD FIELDS — FY2025 REPORTED ACTUALS (US$m unless stated)
A2: Source: Gold Fields FY2025 reviewed results, SEC Form 6-K, 19–20 Feb 2026.
A4: Metric | B4: FY2025 | C4: FY2024 | D4: % change
A5: Revenue | B5: 8751 | C5: 5202 | D5: =B5/C5-1 -> 0.6822376
A6: Average realised gold price (US$/oz) | B6: 3496 | C6: 2418 | D6: =B6/C6-1 -> 0.44582299
A7: Adjusted EBITDA | B7: 5637 | C7: 2847 | D7: =B7/C7-1 -> 0.97997893
A8: Attributable profit | B8: 3567 | C8: 1245 | D8: =B8/C8-1 -> 1.8650602
A9: Headline earnings | B9: 2576 | C9: 1188 | D9: =B9/C9-1 -> 1.1683502
A10: HEPS (US cents) | B10: 288 | C10: 133 | D10: =B10/C10-1 -> 1.1654135
A11: Normalised profit | B11: 2684 | C11: 1227 | D11: =B11/C11-1 -> 1.1874491
A12: Attributable production (Moz) | B12: 2.438 | C12: 2.071 | D12: =B12/C12-1 -> 0.17720908
A13: AISC (US$/oz) | B13: 1645 | C13: 1629 | D13: =B13/C13-1 -> 0.0098219767
A14: AIC (US$/oz) | B14: 1927 | C14: 1873 | D14: =B14/C14-1 -> 0.028830753
A15: Adjusted free cash flow | B15: 2970 | C15: 605 | D15: =B15/C15-1 -> 3.9090909
A16: Capital expenditure | B16: 1399 | C16: 1183 | D16: =B16/C16-1 -> 0.18258664
... A19: Total ordinary dividend (ZAR/share) | B19: 25.5 | C19: 11 | D19: =B19/C19-1 -> 1.3181818
A21: FY2024 ordinary dividend shown as indicative R11.00 (prior-year base). FY2025 also paid a ~R4.50 special dividend; total shareholder distributions ~US$1.7bn (54% of adjusted FCF).
