Workbook

Sheet Cover & Sources
B2: GOLD FIELDS LIMITED (JSE: GFI - NYSE: GFI)
B3: Rand-weakness & load-shedding scenario model - FY2026e / FY2027e
B4: Internal Investment-Committee working model - 18 June 2026 - Reporting currency: US$ (Dec year-end)
B6: Sector lens applied: jse-sector-mining (Basic Materials -> Mining -> Gold).
B8: HOW TO USE THIS MODEL
B9: - Change only the BLUE input cells on 'Assumptions'. Every output on 'Scenario Model' re-runs automatically.
B10: - Four scenarios run side by side for FY2026e and FY2027e: Base, Weaker Rand, Load-shedding, Combined (both shocks).
B11: - Gold price is held flat across the four scenarios within each year so ONLY the two South-African levers move:
B12: USD/ZAR (via South Deep's ZAR cost base) and load-shedding (via South Deep volume + AISC).
B13: - FY2025A is the reported actual, used to calibrate the method. All forward figures are analyst estimates (e).
B15: THE KEY STRUCTURAL NUANCE (why group USD sensitivity is muted)
B16: - Gold Fields REPORTS in US dollars and sells gold at a US-dollar price, so group REVENUE does not change when the rand moves.
... B40: For informational purposes only — not investment advice; prepared by internal research from public disclosures. Figures reported in ZAR unless stated. Reviewed vs audited status is noted per company. Forward figures and scenario levels are analyst estimates (e), not company guidance. Share/commodity prices via web search may be delayed — there is no live JSE feed here. Confirm the fund's dealing-period status before acting.

Sheet FY2025 Actuals
B1: GOLD FIELDS - FY2025 REPORTED ACTUALS (US$m unless stated)
B2: Source: S1 - Gold Fields FY2025 reviewed results, SEC Form 6-K, 19-20 Feb 2026. SACRED ACTUALS (verbatim).
B4: Metric | C4: FY2025 | D4: FY2024 | E4: % change | F4: Source
B5: Revenue (managed basis) | C5: 8751 | D5: 5202 | E5: =C5/D5-1 -> 0.6822376 | F5: S1
B6: Revenue (gold-only proxy = price x oz) | C6: 8523 | D6: n/a | E6: - | F6: S1
B7: Average realised gold price (US$/oz) | C7: 3496 | D7: 2418 | E7: =C7/D7-1 -> 0.44582299 | F7: S1
B8: Adjusted EBITDA | C8: 5637 | D8: 2847 | E8: =C8/D8-1 -> 0.97997893 | F8: S1
B9: Attributable profit (incl ~US$808m Gruyere one-off) | C9: 3567 | D9: 1245 | E9: =C9/D9-1 -> 1.8650602 | F9: S1
B10: Normalised profit | C10: 2684 | D10: 1227 | E10: =C10/D10-1 -> 1.1874491 | F10: S1
B11: Attributable production (Moz) | C11: 2.438 | D11: 2.071 | E11: =C11/D11-1 -> 0.17720908 | F11: S1
B12: Group AISC (US$/oz) | C12: 1645 | D12: 1629 | E12: =C12/D12-1 -> 0.0098219767 | F12: S1
B13: AIC - all-in cost (US$/oz) | C13: 1927 | D13: 1873 | E13: =C13/D13-1 -> 0.028830753 | F13: S1
B14: Adjusted free cash flow | C14: 2970 | D14: 605 | E14: =C14/D14-1 -> 3.9090909 | F14: S1
B15: Sustaining capex | C15: 1029 | D15: n/a | E15: - | F15: S1
B16: Net debt (incl leases) | C16: 1442 | D16: 2086 | E16: =C16/D16-1 -> -0.30872483 | F16: S1
B17: Net debt / adj EBITDA (x) | C17: 0.26 | D17: 0.73 | E17: =C17/D17-1 -> -0.64383562 | F17: S1
B18: USD/ZAR (period average) | C18: 18.3 | D18: n/a | E18: - | F18: S1
B19: Total ordinary dividend (ZAR/share) | C19: 25.5 | D19: 11 | E19: =C19/D19-1 -> 1.3181818 | F19: S1
B21: FY2024 dividend indicative R11.00. FY2025 also paid ~R4.50 special dividend; total distributions ~US$1.7bn (~54% adj FCF). Gold-only proxy excludes Cerro Corona by-product credits.

Sheet Assumptions
B1: GOLD FIELDS - SCENARIO ASSUMPTIONS (edit BLUE cells)
B2: FY2025A = reported actual (S1, calibration). Forward figures are analyst estimates (e). Gold held flat across scenarios to isolate the two SA levers.
C4: FY2025A | D4: Base | F4: Weaker Rand | H4: Load-shedding | J4: Combined
B5: Driver (blue = scenario input) | C5: 2025A | D5: 2026e | E5: 2027e | F5: 2026e | G5: 2027e | H5: 2026e | I5: 2027e | J5: 2026e | K5: 2027e
B6: Realised gold price (US$/oz) | C6: 3496 | D6: 4300 | E6: 4400 | F6: 4300 | G6: 4400 | H6: 4300 | I6: 4400 | J6: 4300 | K6: 4400
B7: Attributable production (Moz) | C7: 2.438 | D7: 2.5 | E7: 2.55 | F7: 2.5 | G7: 2.55 | H7: 2.49 | I7: 2.54 | J7: 2.49 | K7: 2.54
B8: Group AISC - all-in sustaining (US$/oz) | C8: 1645 | D8: 1900 | E8: 1880 | F8: 1860 | G8: 1838 | H8: 1920 | I8: 1900 | J8: 1880 | K8: 1858
B9: AIC - all-in cost (US$/oz) | C9: 1927 | D9: 2200 | E9: 2170 | F9: 2160 | G9: 2128 | H9: 2220 | I9: 2190 | J9: 2180 | K9: 2148
B10: Sustaining capex (US$m) | C10: 1029 | D10: 1350 | E10: 1320 | F10: 1350 | G10: 1320 | H10: 1350 | I10: 1320 | J10: 1350 | K10: 1320
B11: Effective cash tax rate (%) | C11: 0.31 | D11: 0.3 | E11: 0.3 | F11: 0.3 | G11: 0.3 | H11: 0.3 | I11: 0.3 | J11: 0.3 | K11: 0.3
B12: USD/ZAR (period average) | C12: 18.3 | D12: 16.5 | E12: 16.8 | F12: 21 | G12: 22 | H12: 16.5 | I12: 16.8 | J12: 21 | K12: 22
B13: Shareholder payout (% of FCF proxy) | C13: 0.54 | D13: 0.45 | E13: 0.45 | F13: 0.45 | G13: 0.45 | H13: 0.42 | I13: 0.42 | J13: 0.42 | K13: 0.42
B15: SCENARIO DRIVERS (estimates, e):
B16: Weaker Rand: USD/ZAR to ~21 (2026e)/~22 (2027e), ~25-35% weaker than ~16.2 spot. South Deep's ZAR cost base translates to fewer USD => group AISC eases ~US$40/oz (e). Group revenue unchanged (USD). Net USD tailwind ~+US$100m EBITDA; rand-translated EBITDA/dividend +25-30%.
B17: Load-shedding: Stage 4-6 returns. Localised to South Deep (~14% of group oz): ~5-15koz lost + diesel self-generation adds ~US$50-150/oz to its AISC => ~+US$20/oz group AISC, ~-5koz group output. Khanyisa 50MW solar (~8.5% of grid cost) cushions but daytime-only. Net USD headwind ~-US$50-120m EBITDA.
B18: Combined: both shocks together (they tend to co-arrive). Weak-rand cost tailwind partly offsets the load-shedding drag => near-wash in USD; large uplift in ZAR. Base sits between, on company guidance.

Sheet Scenario Model
B1: GOLD FIELDS - SCENARIO MODEL OUTPUT (US$m unless stated)
B2: Green = link to Assumptions; black = formula. Re-runs when blue inputs change. All forward values (e). Source S1/S6.
C4: FY2025A | D4: Base | F4: Weaker Rand | H4: Load-shedding | J4: Combined
B5: Output | C5: 2025A | D5: 2026e | E5: 2027e | F5: 2026e | G5: 2027e | H5: 2026e | I5: 2027e | J5: 2026e | K5: 2027e | L5: Source
B6: Realised gold price (US$/oz) | C6: =Assumptions!C6 -> 3496 | D6: =Assumptions!D6 -> 4300 | E6: =Assumptions!E6 -> 4400 | F6: =Assumptions!F6 -> 4300 | G6: =Assumptions!G6 -> 4400 | H6: =Assumptions!H6 -> 4300 | I6: =Assumptions!I6 -> 4400 | J6: =Assumptions!J6 -> 4300 | K6: =Assumptions!K6 -> 4400 | L6: S6
B7: Attributable production (Moz) | C7: =Assumptions!C7 -> 2.438 | D7: =Assumptions!D7 -> 2.5 | E7: =Assumptions!E7 -> 2.55 | F7: =Assumptions!F7 -> 2.5 | G7: =Assumptions!G7 -> 2.55 | H7: =Assumptions!H7 -> 2.49 | I7: =Assumptions!I7 -> 2.54 | J7: =Assumptions!J7 -> 2.49 | K7: =Assumptions!K7 -> 2.54 | L7: S6
B8: Group AISC (US$/oz) | C8: =Assumptions!C8 -> 1645 | D8: =Assumptions!D8 -> 1900 | E8: =Assumptions!E8 -> 1880 | F8: =Assumptions!F8 -> 1860 | G8: =Assumptions!G8 -> 1838 | H8: =Assumptions!H8 -> 1920 | I8: =Assumptions!I8 -> 1900 | J8: =Assumptions!J8 -> 1880 | K8: =Assumptions!K8 -> 1858 | L8: S6
B9: USD/ZAR (period average) | C9: =Assumptions!C12 -> 18.3 | D9: =Assumptions!D12 -> 16.5 | E9: =Assumptions!E12 -> 16.8 | F9: =Assumptions!F12 -> 21 | G9: =Assumptions!G12 -> 22 | H9: =Assumptions!H12 -> 16.5 | I9: =Assumptions!I12 -> 16.8 | J9: =Assumptions!J12 -> 21 | K9: =Assumptions!K12 -> 22 | L9: S6
B10: Revenue (gold-only proxy) | C10: =C6*C7 -> 8523.248 | D10: =D6*D7 -> 10750 | E10: =E6*E7 -> 11220 | F10: =F6*F7 -> 10750 | G10: =G6*G7 -> 11220 | H10: =H6*H7 -> 10707 | I10: =I6*I7 -> 11176 | J10: =J6*J7 -> 10707 | K10: =K6*K7 -> 11176 | L10: (e)
B11: less: AISC cash cost | C11: =-C8*C7 -> -4010.51 | D11: =-D8*D7 -> -4750 | E11: =-E8*E7 -> -4794 | F11: =-F8*F7 -> -4650 | G11: =-G8*G7 -> -4686.9 | H11: =-H8*H7 -> -4780.8 | I11: =-I8*I7 -> -4826 | J11: =-J8*J7 -> -4681.2 | K11: =-K8*K7 -> -4719.32 | L11: (e)
B12: Group AISC margin | C12: =C10-C8*C7 -> 4512.738 | D12: =D10-D8*D7 -> 6000 | E12: =E10-E8*E7 -> 6426 | F12: =F10-F8*F7 -> 6100 | G12: =G10-G8*G7 -> 6533.1 | H12: =H10-H8*H7 -> 5926.2 | I12: =I10-I8*I7 -> 6350 | J12: =J10-J8*J7 -> 6025.8 | K12: =K10-K8*K7 -> 6456.68 | L12: (e)
B13: add: sustaining capex | C13: =Assumptions!C10 -> 1029 | D13: =Assumptions!D10 -> 1350 | E13: =Assumptions!E10 -> 1320 | F13: =Assumptions!F10 -> 1350 | G13: =Assumptions!G10 -> 1320 | H13: =Assumptions!H10 -> 1350 | I13: =Assumptions!I10 -> 1320 | J13: =Assumptions!J10 -> 1350 | K13: =Assumptions!K10 -> 1320 | L13: S6
B14: EBITDA (e) | C14: =C12+C13 -> 5541.738 | D14: =D12+D13 -> 7350 | E14: =E12+E13 -> 7746 | F14: =F12+F13 -> 7450 | G14: =G12+G13 -> 7853.1 | H14: =H12+H13 -> 7276.2 | I14: =I12+I13 -> 7670 | J14: =J12+J13 -> 7375.8 | K14: =K12+K13 -> 7776.68 | L14: (e)
B15: EBITDA margin (%) | C15: =C14/C10 -> 0.65019087 | D15: =D14/D10 -> 0.68372093 | E15: =E14/E10 -> 0.69037433 | F15: =F14/F10 -> 0.69302326 | G15: =G14/G10 -> 0.69991979 | H15: =H14/H10 -> 0.67957411 | I15: =I14/I10 -> 0.68629205 | J15: =J14/J10 -> 0.68887644 | K15: =K14/K10 -> 0.69583751 | L15: (e)
B16: EBITDA vs Base, same year (e) | C16: - | D16: - | E16: - | F16: =F14-D14 -> 100 | G16: =G14-E14 -> 107.1 | H16: =H14-D14 -> -73.8 | I16: =I14-E14 -> -76 | J16: =J14-D14 -> 25.8 | K16: =K14-E14 -> 30.68 | L16: (e)
B17: EBITDA in ZAR bn (e) | C17: =C14*C9/1000 -> 101.41381 | D17: =D14*D9/1000 -> 121.275 | E17: =E14*E9/1000 -> 130.1328 | F17: =F14*F9/1000 -> 156.45 | G17: =G14*G9/1000 -> 172.7682 | H17: =H14*H9/1000 -> 120.0573 | I17: =I14*I9/1000 -> 128.856 | J17: =J14*J9/1000 -> 154.8918 | K17: =K14*K9/1000 -> 171.08696 | L17: (e)
B18: All-in margin, pre-tax (e) | C18: =C10-Assumptions!C9*C7 -> 3825.222 | D18: =D10-Assumptions!D9*D7 -> 5250 | E18: =E10-Assumptions!E9*E7 -> 5686.5 | F18: =F10-Assumptions!F9*F7 -> 5350 | G18: =G10-Assumptions!G9*G7 -> 5793.6 | H18: =H10-Assumptions!H9*H7 -> 5179.2 | I18: =I10-Assumptions!I9*I7 -> 5613.4 | J18: =J10-Assumptions!J9*J7 -> 5278.8 | K18: =K10-Assumptions!K9*K7 -> 5720.08 | L18: (e)
B19: less: cash tax (e) | C19: =-C18*Assumptions!C11 -> -1185.8188 | D19: =-D18*Assumptions!D11 -> -1575 | E19: =-E18*Assumptions!E11 -> -1705.95 | F19: =-F18*Assumptions!F11 -> -1605 | G19: =-G18*Assumptions!G11 -> -1738.08 | H19: =-H18*Assumptions!H11 -> -1553.76 | I19: =-I18*Assumptions!I11 -> -1684.02 | J19: =-J18*Assumptions!J11 -> -1583.64 | K19: =-K18*Assumptions!K11 -> -1716.024 | L19: (e)
B20: Post-tax all-in FCF proxy (e) | C20: =C18*(1-Assumptions!C11) -> 2639.4032 | D20: =D18*(1-Assumptions!D11) -> 3675 | E20: =E18*(1-Assumptions!E11) -> 3980.55 | F20: =F18*(1-Assumptions!F11) -> 3745 | G20: =G18*(1-Assumptions!G11) -> 4055.52 | H20: =H18*(1-Assumptions!H11) -> 3625.44 | I20: =I18*(1-Assumptions!I11) -> 3929.38 | J20: =J18*(1-Assumptions!J11) -> 3695.16 | K20: =K18*(1-Assumptions!K11) -> 4004.056 | L20: (e)
B21: FCF vs Base, same year (e) | C21: - | D21: - | E21: - | F21: =F20-D20 -> 70 | G21: =G20-E20 -> 74.97 | H21: =H20-D20 -> -49.56 | I21: =I20-E20 -> -51.17 | J21: =J20-D20 -> 20.16 | K21: =K20-E20 -> 23.506 | L21: (e)
B22: Implied shareholder returns (e) | C22: =C20*Assumptions!C13 -> 1425.2777 | D22: =D20*Assumptions!D13 -> 1653.75 | E22: =E20*Assumptions!E13 -> 1791.2475 | F22: =F20*Assumptions!F13 -> 1685.25 | G22: =G20*Assumptions!G13 -> 1824.984 | H22: =H20*Assumptions!H13 -> 1522.6848 | I22: =I20*Assumptions!I13 -> 1650.3396 | J22: =J20*Assumptions!J13 -> 1551.9672 | K22: =K20*Assumptions!K13 -> 1681.7035 | L22: (e)
B24: SENSITIVITY (group, at ~2.5Moz)
B25: Gold price: +/-US$100/oz | D25: +/- US$250m EBITDA (e) | L25: (e)
B26: Group AISC: +/-US$100/oz | D26: -/+ US$250m EBITDA (e) | L26: (e)
B27: Weaker rand ~25-35% (to R20-22) | D27: +~US$100m USD EBITDA (e); rand EBITDA/div +25-30% (e) | L27: (e)
B28: Load-shedding Stage 4-6 returns | D28: -~US$50-120m USD EBITDA (e) | L28: (e)

Sheet Positive Outcomes
B1: POSITIVE OUTCOMES ASSESSMENT (ESG & Stakeholder) - informational, non-financial
B2: Per AllWeather's 'Investing in positive outcomes' philosophy. This lens does NOT change, gate or tie-break the financial conclusion. AllWeather view = judgement, not sourced fact.
B4: Pillar | C4: Evidence | D4: Source
B5: ESG / impact | C5: Net-zero by 2050 (Paris-aligned); Scope 1&2 -30% net / -50% absolute by 2030, Scope 3 -10% net by 2030. By 2024 only ~4% Scope 1&2 cut vs 2016 baseline (production +5% over the span) - most reduction still to come. Tailings, water stewardship and 30% female workforce are named 2030 goals. | D5: S3
B6: ESG / impact | C6: South Deep 50MW Khanyisa solar runs at ~8.5% of Eskom grid cost and exports surplus power; battery + wind extension under evaluation. Lowers emissions AND hardens the mine against the load-shedding risk modelled here. | D6: S3
B7: Stakeholder | C7: Safety: five consecutive quarters fatality-free, though three serious injuries most recent quarter - improving, not solved. | D7: S3
B8: Stakeholder | C8: Thusano employee share trust holds ~10.75% of GFIMSA (SA holdco), paying employee dividends; South Deep Education & Community Trusts fund jobs, adult education, infrastructure and small-enterprise development. | D8: S3
B9: AllWeather view | C9: Climate ambition sound and renewables build genuine, but thin 2024 progress vs 2016 baseline is the item to scrutinise. Trust structures are a tangible differentiated positive; open question is wage/workforce/B-BBEE data - not on disk (coverage gap). Judgement, not sourced fact. | D9: -
